[
  {
    "_id": "og35g3XlNoiPQER_CDK8tLp7-wJQ",
    "_legacy_id": 1,
    "openid": "og35g3XlNoiPQER_CDK8tLp7-wJQ",
    "nickName": "小锚点和他的老婆",
    "avatarUrl": "https://oss-1357612648.cos.ap-shanghai.myqcloud.com/users/avatars/1773442454474_3853b6b7399dccc3.jpeg",
    "phone": "",
    "role_level": 0,
    "distributor_level": 1,
    "points": 2,
    "wallet_balance": 0,
    "referrer_openid": "",
    "my_invite_code": "",
    "created_at": "2026-03-13T22:54:08.000Z",
    "updated_at": "2026-03-29T11:04:01.000Z"
  },
  {
    "_id": "og35g3cWRtlnzYVD750nsW2d1sAk",
    "_legacy_id": 2,
    "openid": "og35g3cWRtlnzYVD750nsW2d1sAk",
    "nickName": "微信用户",
    "avatarUrl": "",
    "phone": "",
    "role_level": 3,
    "distributor_level": 3,
    "points": 0,
    "wallet_balance": 0,
    "referrer_openid": "",
    "my_invite_code": "",
    "created_at": "2026-03-13T23:38:13.000Z",
    "updated_at": "2026-03-29T11:04:01.000Z"
  },
  {
    "_id": "oc0ZD3Y5yrF5ezpwwSPUtkJWna1Q",
    "_legacy_id": 3,
    "openid": "oc0ZD3Y5yrF5ezpwwSPUtkJWna1Q",
    "nickName": "小锚点和他的老婆",
    "avatarUrl": "https://oss-1357612648.cos.ap-shanghai.myqcloud.com/users/avatars/1774869057302_1e47b7f91d896027.jpeg",
    "phone": "",
    "role_level": 5,
    "distributor_level": 3,
    "points": 1705,
    "wallet_balance": 880,
    "referrer_openid": "",
    "my_invite_code": "",
    "created_at": "2026-03-21T02:42:13.000Z",
    "updated_at": "2026-04-07T02:15:04.000Z"
  },
  {
    "_id": "oc0ZD3fCGjctX5s5HHbsXvnjKYlE",
    "_legacy_id": 4,
    "openid": "oc0ZD3fCGjctX5s5HHbsXvnjKYlE",
    "nickName": "微信用户",
    "avatarUrl": "/assets/images/default-avatar.svg",
    "phone": "",
    "role_level": 0,
    "distributor_level": 1,
    "points": 2,
    "wallet_balance": 0,
    "referrer_openid": "",
    "my_invite_code": "",
    "created_at": "2026-03-21T02:57:03.000Z",
    "updated_at": "2026-03-31T15:33:34.000Z"
  },
  {
    "_id": "oc0ZD3eEUfbv8095hzwf7NWdBsoI",
    "_legacy_id": 5,
    "openid": "oc0ZD3eEUfbv8095hzwf7NWdBsoI",
    "nickName": "微信用户",
    "avatarUrl": "/assets/images/default-avatar.svg",
    "phone": "",
    "role_level": 0,
    "distributor_level": 1,
    "points": 2,
    "wallet_balance": 0,
    "referrer_openid": "",
    "my_invite_code": "",
    "created_at": "2026-03-21T02:57:14.000Z",
    "updated_at": "2026-04-01T04:49:12.000Z"
  },
  {
    "_id": "oc0ZD3R5hbEfSKtMkK9xmPH2XuSw",
    "_legacy_id": 6,
    "openid": "oc0ZD3R5hbEfSKtMkK9xmPH2XuSw",
    "nickName": "微信用户",
    "avatarUrl": "/assets/images/default-avatar.svg",
    "phone": "",
    "role_level": 0,
    "distributor_level": 1,
    "points": 6,
    "wallet_balance": 0,
    "referrer_openid": "",
    "my_invite_code": "",
    "created_at": "2026-03-21T02:57:14.000Z",
    "updated_at": "2026-04-06T15:46:48.000Z"
  },
  {
    "_id": "oc0ZD3RoaOZHNICfVi5zl3DoYExs",
    "_legacy_id": 8,
    "openid": "oc0ZD3RoaOZHNICfVi5zl3DoYExs",
    "nickName": "金水桥",
    "avatarUrl": "https://oss-1357612648.cos.ap-shanghai.myqcloud.com/users/avatars/1774186026704_ee990d2166376cf6.jpg",
    "phone": "",
    "role_level": 7,
    "distributor_level": 1,
    "points": 10,
    "wallet_balance": 0,
    "referrer_openid": "oc0ZD3Y5yrF5ezpwwSPUtkJWna1Q",
    "my_invite_code": "",
    "created_at": "2026-03-21T03:05:56.000Z",
    "updated_at": "2026-04-04T04:26:28.000Z"
  },
  {
    "_id": "oc0ZD3Yg0EuwFCwULsy4TkGqWcDc",
    "_legacy_id": 9,
    "openid": "oc0ZD3Yg0EuwFCwULsy4TkGqWcDc",
    "nickName": "微信用户",
    "avatarUrl": "/assets/images/default-avatar.svg",
    "phone": "",
    "role_level": 0,
    "distributor_level": 1,
    "points": 2,
    "wallet_balance": 0,
    "referrer_openid": "",
    "my_invite_code": "",
    "created_at": "2026-03-21T03:32:01.000Z",
    "updated_at": "2026-04-06T15:46:48.000Z"
  },
  {
    "_id": "oc0ZD3S2ZRCcKsDv8_41QG5Q9Hhs",
    "_legacy_id": 10,
    "openid": "oc0ZD3S2ZRCcKsDv8_41QG5Q9Hhs",
    "nickName": "微信用户",
    "avatarUrl": "/assets/images/default-avatar.svg",
    "phone": "",
    "role_level": 0,
    "distributor_level": 1,
    "points": 2,
    "wallet_balance": 0,
    "referrer_openid": "",
    "my_invite_code": "",
    "created_at": "2026-03-21T03:32:12.000Z",
    "updated_at": "2026-04-06T04:07:13.000Z"
  },
  {
    "_id": "oc0ZD3eAoQ79ccXY3VdCVTmPMmg8",
    "_legacy_id": 11,
    "openid": "oc0ZD3eAoQ79ccXY3VdCVTmPMmg8",
    "nickName": "微信用户",
    "avatarUrl": "/assets/images/default-avatar.svg",
    "phone": "",
    "role_level": 0,
    "distributor_level": 1,
    "points": 4,
    "wallet_balance": 0,
    "referrer_openid": "",
    "my_invite_code": "",
    "created_at": "2026-03-21T08:46:32.000Z",
    "updated_at": "2026-03-30T03:12:16.000Z"
  },
  {
    "_id": "oc0ZD3R3l2ehTv57m9DSIeSSzwcU",
    "_legacy_id": 12,
    "openid": "oc0ZD3R3l2ehTv57m9DSIeSSzwcU",
    "nickName": "wxid_nrysw4xo5qwo12",
    "avatarUrl": "https://oss-1357612648.cos.ap-shanghai.myqcloud.com/users/avatars/1774082926018_4cb1d24400afa01c.png",
    "phone": "",
    "role_level": 0,
    "distributor_level": 1,
    "points": 0,
    "wallet_balance": 0,
    "referrer_openid": "",
    "my_invite_code": "",
    "created_at": "2026-03-21T08:46:46.000Z",
    "updated_at": "2026-03-29T11:04:01.000Z"
  },
  {
    "_id": "oc0ZD3ZyKP7brDHBFSBhUNji-ZaY",
    "_legacy_id": 13,
    "openid": "oc0ZD3ZyKP7brDHBFSBhUNji-ZaY",
    "nickName": "微信用户",
    "avatarUrl": "/assets/images/default-avatar.svg",
    "phone": "",
    "role_level": 0,
    "distributor_level": 1,
    "points": 4,
    "wallet_balance": 0,
    "referrer_openid": "",
    "my_invite_code": "",
    "created_at": "2026-03-21T08:47:00.000Z",
    "updated_at": "2026-03-30T11:05:47.000Z"
  },
  {
    "_id": "oc0ZD3ZQzX9Ndj0mUXdfv-EKgVjM",
    "_legacy_id": 14,
    "openid": "oc0ZD3ZQzX9Ndj0mUXdfv-EKgVjM",
    "nickName": "微信用户",
    "avatarUrl": "/assets/images/default-avatar.svg",
    "phone": "",
    "role_level": 0,
    "distributor_level": 1,
    "points": 2,
    "wallet_balance": 0,
    "referrer_openid": "",
    "my_invite_code": "",
    "created_at": "2026-03-21T09:24:06.000Z",
    "updated_at": "2026-03-29T11:04:01.000Z"
  },
  {
    "_id": "oc0ZD3Rfkbr2boBWs0ElapQFpTco",
    "_legacy_id": 15,
    "openid": "oc0ZD3Rfkbr2boBWs0ElapQFpTco",
    "nickName": "微信用户",
    "avatarUrl": "",
    "phone": "",
    "role_level": 0,
    "distributor_level": 1,
    "points": 0,
    "wallet_balance": 0,
    "referrer_openid": "",
    "my_invite_code": "",
    "created_at": "2026-03-21T09:36:12.000Z",
    "updated_at": "2026-03-29T11:04:01.000Z"
  },
  {
    "_id": "oc0ZD3R8vtLLzxey_3gIOBs6AQhM",
    "_legacy_id": 16,
    "openid": "oc0ZD3R8vtLLzxey_3gIOBs6AQhM",
    "nickName": "wxid_8khbfdaygdka12",
    "avatarUrl": "https://oss-1357612648.cos.ap-shanghai.myqcloud.com/users/avatars/1774086906652_e4b5f438ace881ad.png",
    "phone": "",
    "role_level": 0,
    "distributor_level": 1,
    "points": 0,
    "wallet_balance": 0,
    "referrer_openid": "",
    "my_invite_code": "",
    "created_at": "2026-03-21T09:53:55.000Z",
    "updated_at": "2026-03-29T11:04:01.000Z"
  },
  {
    "_id": "oc0ZD3Uu4w_KvuYYQMob91ql8GK4",
    "_legacy_id": 17,
    "openid": "oc0ZD3Uu4w_KvuYYQMob91ql8GK4",
    "nickName": "王志霞",
    "avatarUrl": "https://oss-1357612648.cos.ap-shanghai.myqcloud.com/users/avatars/1774159865394_5db481e95dc07df8.jpg",
    "phone": "",
    "role_level": 0,
    "distributor_level": 1,
    "points": 0,
    "wallet_balance": 0,
    "referrer_openid": "oc0ZD3RoaOZHNICfVi5zl3DoYExs",
    "my_invite_code": "",
    "created_at": "2026-03-22T06:09:57.000Z",
    "updated_at": "2026-04-03T08:55:17.000Z"
  },
  {
    "_id": "oc0ZD3YsUQ6tnLPSv7CWLwzIkgHg",
    "_legacy_id": 18,
    "openid": "oc0ZD3YsUQ6tnLPSv7CWLwzIkgHg",
    "nickName": "wxid_p0wm1yv1mt3y12",
    "avatarUrl": "https://oss-1357612648.cos.ap-shanghai.myqcloud.com/users/avatars/1774177808769_bf0e69c13905e4f9.png",
    "phone": "",
    "role_level": 0,
    "distributor_level": 1,
    "points": 2,
    "wallet_balance": 0,
    "referrer_openid": "",
    "my_invite_code": "",
    "created_at": "2026-03-22T11:08:52.000Z",
    "updated_at": "2026-03-29T11:04:01.000Z"
  },
  {
    "_id": "oc0ZD3RRGpEnNkIS4Ksg2qPrdNJs",
    "_legacy_id": 19,
    "openid": "oc0ZD3RRGpEnNkIS4Ksg2qPrdNJs",
    "nickName": "微信用户",
    "avatarUrl": "/assets/images/default-avatar.svg",
    "phone": "",
    "role_level": 0,
    "distributor_level": 1,
    "points": 0,
    "wallet_balance": 0,
    "referrer_openid": "",
    "my_invite_code": "",
    "created_at": "2026-03-22T14:45:43.000Z",
    "updated_at": "2026-03-30T09:14:43.000Z"
  },
  {
    "_id": "oc0ZD3Uwa9rRXiWVNcqQ8PzKDSnY",
    "_legacy_id": 20,
    "openid": "oc0ZD3Uwa9rRXiWVNcqQ8PzKDSnY",
    "nickName": "微信用户",
    "avatarUrl": "",
    "phone": "",
    "role_level": 0,
    "distributor_level": 1,
    "points": 0,
    "wallet_balance": 0,
    "referrer_openid": "",
    "my_invite_code": "",
    "created_at": "2026-03-23T01:08:13.000Z",
    "updated_at": "2026-03-29T11:04:01.000Z"
  },
  {
    "_id": "oc0ZD3d1ZkphO0W6ZJXalaBD_fiA",
    "_legacy_id": 21,
    "openid": "oc0ZD3d1ZkphO0W6ZJXalaBD_fiA",
    "nickName": "微信用户",
    "avatarUrl": "",
    "phone": "",
    "role_level": 0,
    "distributor_level": 1,
    "points": 0,
    "wallet_balance": 0,
    "referrer_openid": "",
    "my_invite_code": "",
    "created_at": "2026-03-23T03:21:05.000Z",
    "updated_at": "2026-03-29T11:04:01.000Z"
  },
  {
    "_id": "oc0ZD3U6ngmfB3MLFTYuRiEaYDh4",
    "_legacy_id": 22,
    "openid": "oc0ZD3U6ngmfB3MLFTYuRiEaYDh4",
    "nickName": "微信用户",
    "avatarUrl": "https://oss-1357612648.cos.ap-shanghai.myqcloud.com/users/avatars/1774605158449_e700fd8bb91045c4.jpeg",
    "phone": "",
    "role_level": 7,
    "distributor_level": 1,
    "points": 0,
    "wallet_balance": 0,
    "referrer_openid": "",
    "my_invite_code": "",
    "created_at": "2026-03-25T13:07:32.000Z",
    "updated_at": "2026-03-30T04:17:05.000Z"
  },
  {
    "_id": "oc0ZD3TJVM7Ljzu1Hd8nQdogiuKw",
    "_legacy_id": 23,
    "openid": "oc0ZD3TJVM7Ljzu1Hd8nQdogiuKw",
    "nickName": "微信用户",
    "avatarUrl": "/assets/images/default-avatar.svg",
    "phone": "",
    "role_level": 0,
    "distributor_level": 1,
    "points": 0,
    "wallet_balance": 0,
    "referrer_openid": "",
    "my_invite_code": "",
    "created_at": "2026-03-25T15:30:41.000Z",
    "updated_at": "2026-04-03T01:53:53.000Z"
  },
  {
    "_id": "oc0ZD3duCTWE8n-lBA5ol31nc6QI",
    "_legacy_id": 24,
    "openid": "oc0ZD3duCTWE8n-lBA5ol31nc6QI",
    "nickName": "微信用户",
    "avatarUrl": "/assets/images/default-avatar.svg",
    "phone": "",
    "role_level": 0,
    "distributor_level": 1,
    "points": 2,
    "wallet_balance": 0,
    "referrer_openid": "",
    "my_invite_code": "",
    "created_at": "2026-03-27T05:50:53.000Z",
    "updated_at": "2026-04-06T04:07:37.000Z"
  },
  {
    "_id": "oc0ZD3XEbQjqT-pyRGXIPkarIKmo",
    "_legacy_id": 25,
    "openid": "oc0ZD3XEbQjqT-pyRGXIPkarIKmo",
    "nickName": "微信用户",
    "avatarUrl": "https://oss-1357612648.cos.ap-shanghai.myqcloud.com/users/avatars/1774590730381_a2342c9bd6fb301c.png",
    "phone": "",
    "role_level": 0,
    "distributor_level": 1,
    "points": 0,
    "wallet_balance": 0,
    "referrer_openid": "",
    "my_invite_code": "",
    "created_at": "2026-03-27T05:51:10.000Z",
    "updated_at": "2026-03-29T11:04:01.000Z"
  },
  {
    "_id": "oc0ZD3WV0JUTVWhYdUWLvYP7fYPo",
    "_legacy_id": 26,
    "openid": "oc0ZD3WV0JUTVWhYdUWLvYP7fYPo",
    "nickName": "微信用户",
    "avatarUrl": "",
    "phone": "",
    "role_level": 0,
    "distributor_level": 1,
    "points": 0,
    "wallet_balance": 0,
    "referrer_openid": "",
    "my_invite_code": "",
    "created_at": "2026-03-27T05:54:56.000Z",
    "updated_at": "2026-03-29T11:04:01.000Z"
  },
  {
    "_id": "oc0ZD3RHUf8uL_WtYFgcLOdtGlN4",
    "_legacy_id": 27,
    "openid": "oc0ZD3RHUf8uL_WtYFgcLOdtGlN4",
    "nickName": "爱笑的甜甜",
    "avatarUrl": "https://oss-1357612648.cos.ap-shanghai.myqcloud.com/users/avatars/1774605468021_eefd0ce94867056c.jpeg",
    "phone": "",
    "role_level": 0,
    "distributor_level": 1,
    "points": 201,
    "wallet_balance": 0,
    "referrer_openid": "oc0ZD3XxzPISJj9epmRvGrOApzQ4",
    "my_invite_code": "",
    "created_at": "2026-03-27T08:57:14.000Z",
    "updated_at": "2026-04-04T09:13:54.000Z"
  },
  {
    "_id": "oc0ZD3XxzPISJj9epmRvGrOApzQ4",
    "_legacy_id": 28,
    "openid": "oc0ZD3XxzPISJj9epmRvGrOApzQ4",
    "nickName": "曦曦是大太阳",
    "avatarUrl": "https://oss-1357612648.cos.ap-shanghai.myqcloud.com/users/avatars/1774601935991_63281cb5512144f1.jpeg",
    "phone": "",
    "role_level": 4,
    "distributor_level": 1,
    "points": 2,
    "wallet_balance": 110,
    "referrer_openid": "oc0ZD3Y5yrF5ezpwwSPUtkJWna1Q",
    "my_invite_code": "",
    "created_at": "2026-03-27T08:58:02.000Z",
    "updated_at": "2026-04-05T06:06:31.000Z"
  },
  {
    "_id": "oc0ZD3XRxs2M5e7qiFntdpAM8OzI",
    "_legacy_id": 29,
    "openid": "oc0ZD3XRxs2M5e7qiFntdpAM8OzI",
    "nickName": "微信用户",
    "avatarUrl": "",
    "phone": "",
    "role_level": 0,
    "distributor_level": 1,
    "points": 0,
    "wallet_balance": 0,
    "referrer_openid": "",
    "my_invite_code": "",
    "created_at": "2026-03-27T09:01:39.000Z",
    "updated_at": "2026-03-29T11:04:01.000Z"
  },
  {
    "_id": "oc0ZD3f9L3Gqjp00fGXo0tOMILjY",
    "_legacy_id": 30,
    "openid": "oc0ZD3f9L3Gqjp00fGXo0tOMILjY",
    "nickName": "微信用户",
    "avatarUrl": "/assets/images/default-avatar.svg",
    "phone": "",
    "role_level": 0,
    "distributor_level": 1,
    "points": 0,
    "wallet_balance": 0,
    "referrer_openid": "",
    "my_invite_code": "",
    "created_at": "2026-03-28T09:48:59.000Z",
    "updated_at": "2026-03-29T11:04:01.000Z"
  },
  {
    "_id": "oc0ZD3aupefF5iBjgDTKp6URTs4w",
    "_legacy_id": 31,
    "openid": "oc0ZD3aupefF5iBjgDTKp6URTs4w",
    "nickName": "微信用户",
    "avatarUrl": "/assets/images/default-avatar.svg",
    "phone": "",
    "role_level": 0,
    "distributor_level": 1,
    "points": 0,
    "wallet_balance": 0,
    "referrer_openid": "",
    "my_invite_code": "",
    "created_at": "2026-03-28T10:25:04.000Z",
    "updated_at": "2026-04-06T15:46:37.000Z"
  },
  {
    "_id": "oc0ZD3YmjmLIyhkdg0QwnNgJ1mPA",
    "_legacy_id": 32,
    "openid": "oc0ZD3YmjmLIyhkdg0QwnNgJ1mPA",
    "nickName": "微信用户",
    "avatarUrl": "/assets/images/default-avatar.svg",
    "phone": "",
    "role_level": 0,
    "distributor_level": 1,
    "points": 0,
    "wallet_balance": 0,
    "referrer_openid": "",
    "my_invite_code": "",
    "created_at": "2026-03-28T10:25:13.000Z",
    "updated_at": "2026-03-29T11:04:01.000Z"
  },
  {
    "_id": "oc0ZD3StXjzM_88uNC4D6NqRWiqQ",
    "_legacy_id": 33,
    "openid": "oc0ZD3StXjzM_88uNC4D6NqRWiqQ",
    "nickName": "微信用户",
    "avatarUrl": "/assets/images/default-avatar.svg",
    "phone": "",
    "role_level": 0,
    "distributor_level": 1,
    "points": 0,
    "wallet_balance": 0,
    "referrer_openid": "",
    "my_invite_code": "",
    "created_at": "2026-03-28T14:35:18.000Z",
    "updated_at": "2026-03-29T11:04:01.000Z"
  },
  {
    "_id": "oc0ZD3fMYKj1-EFNHe48SaPu_kb4",
    "_legacy_id": 34,
    "openid": "oc0ZD3fMYKj1-EFNHe48SaPu_kb4",
    "nickName": "微信用户",
    "avatarUrl": "/assets/images/default-avatar.svg",
    "phone": "",
    "role_level": 0,
    "distributor_level": 1,
    "points": 0,
    "wallet_balance": 0,
    "referrer_openid": "",
    "my_invite_code": "",
    "created_at": "2026-03-29T02:43:48.000Z",
    "updated_at": "2026-03-29T11:04:01.000Z"
  },
  {
    "_id": "oc0ZD3aaUE6owhlKUB3O5SEGpGVg",
    "_legacy_id": 35,
    "openid": "oc0ZD3aaUE6owhlKUB3O5SEGpGVg",
    "nickName": "微信用户",
    "avatarUrl": "/assets/images/default-avatar.svg",
    "phone": "",
    "role_level": 0,
    "distributor_level": 1,
    "points": 0,
    "wallet_balance": 0,
    "referrer_openid": "",
    "my_invite_code": "",
    "created_at": "2026-03-29T02:58:49.000Z",
    "updated_at": "2026-03-29T11:04:01.000Z"
  },
  {
    "_id": "oc0ZD3bWzY7Xcyj02iWm4lyKfBCE",
    "_legacy_id": 36,
    "openid": "oc0ZD3bWzY7Xcyj02iWm4lyKfBCE",
    "nickName": "微信用户",
    "avatarUrl": "https://oss-1357612648.cos.ap-shanghai.myqcloud.com/users/avatars/1774791733990_91077f386b086591.jpeg",
    "phone": "",
    "role_level": 0,
    "distributor_level": 1,
    "points": 0,
    "wallet_balance": 0,
    "referrer_openid": "oc0ZD3Y5yrF5ezpwwSPUtkJWna1Q",
    "my_invite_code": "",
    "created_at": "2026-03-29T03:45:34.000Z",
    "updated_at": "2026-03-30T03:04:01.000Z"
  },
  {
    "_id": "oc0ZD3cwr0VoxVi9Uw7M4jjwDbZY",
    "_legacy_id": 37,
    "openid": "oc0ZD3cwr0VoxVi9Uw7M4jjwDbZY",
    "nickName": "微信用户",
    "avatarUrl": "/assets/images/default-avatar.svg",
    "phone": "",
    "role_level": 0,
    "distributor_level": 1,
    "points": 0,
    "wallet_balance": 0,
    "referrer_openid": "",
    "my_invite_code": "",
    "created_at": "2026-03-29T05:12:07.000Z",
    "updated_at": "2026-03-29T11:04:01.000Z"
  },
  {
    "_id": "oc0ZD3f58ftMEQbxq5_kVTF1ElXo",
    "_legacy_id": 38,
    "openid": "oc0ZD3f58ftMEQbxq5_kVTF1ElXo",
    "nickName": "问小兰",
    "avatarUrl": "https://oss-1357612648.cos.ap-shanghai.myqcloud.com/materials/1774767923815_dc6e31ff743275ba.jpg",
    "phone": "",
    "role_level": 0,
    "distributor_level": 1,
    "points": 0,
    "wallet_balance": 0,
    "referrer_openid": "oc0ZD3RoaOZHNICfVi5zl3DoYExs",
    "my_invite_code": "",
    "created_at": "2026-03-29T09:16:27.000Z",
    "updated_at": "2026-03-29T11:04:01.000Z"
  },
  {
    "_id": "oc0ZD3YxUt8bzRCWwXqMkp3D2CQY",
    "_legacy_id": 39,
    "openid": "oc0ZD3YxUt8bzRCWwXqMkp3D2CQY",
    "nickName": "Vian冠宇",
    "avatarUrl": "https://oss-1357612648.cos.ap-shanghai.myqcloud.com/users/avatars/1774790468603_5edb998f519d913a.png",
    "phone": "",
    "role_level": 0,
    "distributor_level": 1,
    "points": 0,
    "wallet_balance": 0,
    "referrer_openid": "",
    "my_invite_code": "",
    "created_at": "2026-03-29T13:00:33.000Z",
    "updated_at": "2026-03-29T13:21:08.000Z"
  },
  {
    "_id": "oc0ZD3dUeKhSZP6CMtRtgM4ilG3Q",
    "_legacy_id": 40,
    "openid": "oc0ZD3dUeKhSZP6CMtRtgM4ilG3Q",
    "nickName": "微信用户",
    "avatarUrl": "https://oss-1357612648.cos.ap-shanghai.myqcloud.com/materials/1774767923815_dc6e31ff743275ba.jpg",
    "phone": "",
    "role_level": 0,
    "distributor_level": 1,
    "points": 0,
    "wallet_balance": 0,
    "referrer_openid": "",
    "my_invite_code": "",
    "created_at": "2026-03-29T13:00:34.000Z",
    "updated_at": "2026-03-29T13:01:32.000Z"
  },
  {
    "_id": "oc0ZD3VcqiZEYUq0fuoxs0_voozI",
    "_legacy_id": 41,
    "openid": "oc0ZD3VcqiZEYUq0fuoxs0_voozI",
    "nickName": "傅泽瑞_Ryen",
    "avatarUrl": "https://oss-1357612648.cos.ap-shanghai.myqcloud.com/users/avatars/1774790209038_a043bfafc341b99c.jpg",
    "phone": "",
    "role_level": 0,
    "distributor_level": 1,
    "points": 0,
    "wallet_balance": 0,
    "referrer_openid": "oc0ZD3aHikFsynVAgwqQBb8ze-JQ",
    "my_invite_code": "",
    "created_at": "2026-03-29T13:12:54.000Z",
    "updated_at": "2026-04-05T15:43:56.000Z"
  },
  {
    "_id": "oc0ZD3eyCZC5z6ulOuEpm_kbuMUQ",
    "_legacy_id": 42,
    "openid": "oc0ZD3eyCZC5z6ulOuEpm_kbuMUQ",
    "nickName": "follower",
    "avatarUrl": "https://oss-1357612648.cos.ap-shanghai.myqcloud.com/users/avatars/1774870146863_cb96e8ccdd02745a.jpeg",
    "phone": "",
    "role_level": 0,
    "distributor_level": 1,
    "points": 0,
    "wallet_balance": 0,
    "referrer_openid": "oc0ZD3fqS26hEFVgq0z_RzMBqCTI",
    "my_invite_code": "",
    "created_at": "2026-03-29T13:16:09.000Z",
    "updated_at": "2026-03-30T11:29:17.000Z"
  },
  {
    "_id": "oc0ZD3fqS26hEFVgq0z_RzMBqCTI",
    "_legacy_id": 43,
    "openid": "oc0ZD3fqS26hEFVgq0z_RzMBqCTI",
    "nickName": "八宝周",
    "avatarUrl": "https://oss-1357612648.cos.ap-shanghai.myqcloud.com/materials/1774767923815_dc6e31ff743275ba.jpg",
    "phone": "",
    "role_level": 3,
    "distributor_level": 1,
    "points": 0,
    "wallet_balance": 0,
    "referrer_openid": "oc0ZD3XxzPISJj9epmRvGrOApzQ4",
    "my_invite_code": "",
    "created_at": "2026-03-29T13:16:35.000Z",
    "updated_at": "2026-04-05T16:08:19.000Z"
  },
  {
    "_id": "oc0ZD3aHikFsynVAgwqQBb8ze-JQ",
    "_legacy_id": 44,
    "openid": "oc0ZD3aHikFsynVAgwqQBb8ze-JQ",
    "nickName": "落痕",
    "avatarUrl": "https://oss-1357612648.cos.ap-shanghai.myqcloud.com/users/avatars/1774850162915_d702a62443c790f7.jpeg",
    "phone": "",
    "role_level": 0,
    "distributor_level": 1,
    "points": 0,
    "wallet_balance": 0,
    "referrer_openid": "",
    "my_invite_code": "",
    "created_at": "2026-03-29T13:16:53.000Z",
    "updated_at": "2026-03-31T08:20:37.000Z"
  },
  {
    "_id": "oc0ZD3Yw5MwjDzFi_yF7B7a8Z2mw",
    "_legacy_id": 45,
    "openid": "oc0ZD3Yw5MwjDzFi_yF7B7a8Z2mw",
    "nickName": "子敬变形记",
    "avatarUrl": "https://oss-1357612648.cos.ap-shanghai.myqcloud.com/users/avatars/1774797458602_a4d7d3d17ff75051.jpeg",
    "phone": "",
    "role_level": 0,
    "distributor_level": 1,
    "points": 0,
    "wallet_balance": 0,
    "referrer_openid": "oc0ZD3XxzPISJj9epmRvGrOApzQ4",
    "my_invite_code": "",
    "created_at": "2026-03-29T13:19:11.000Z",
    "updated_at": "2026-04-06T16:09:18.000Z"
  },
  {
    "_id": "oc0ZD3enc_TcSaiTvZEwV8ugnj98",
    "_legacy_id": 46,
    "openid": "oc0ZD3enc_TcSaiTvZEwV8ugnj98",
    "nickName": "www",
    "avatarUrl": "https://oss-1357612648.cos.ap-shanghai.myqcloud.com/users/avatars/1774862156820_2ab567c203b6869b.jpg",
    "phone": "",
    "role_level": 0,
    "distributor_level": 1,
    "points": 0,
    "wallet_balance": 0,
    "referrer_openid": "oc0ZD3YpHJvUxAK79fMjRKVlrvhk",
    "my_invite_code": "",
    "created_at": "2026-03-29T13:20:03.000Z",
    "updated_at": "2026-03-30T09:16:03.000Z"
  },
  {
    "_id": "oc0ZD3ZyOQ8EKkebXOHpKwnOIfCc",
    "_legacy_id": 47,
    "openid": "oc0ZD3ZyOQ8EKkebXOHpKwnOIfCc",
    "nickName": "竹行鹤.",
    "avatarUrl": "https://oss-1357612648.cos.ap-shanghai.myqcloud.com/users/avatars/1774844614872_ef576b45237d810c.jpeg",
    "phone": "",
    "role_level": 0,
    "distributor_level": 1,
    "points": 0,
    "wallet_balance": 0,
    "referrer_openid": "oc0ZD3VcqiZEYUq0fuoxs0_voozI",
    "my_invite_code": "",
    "created_at": "2026-03-29T13:21:14.000Z",
    "updated_at": "2026-03-31T05:30:17.000Z"
  },
  {
    "_id": "oc0ZD3aCeGoAPqR1gY4SpYo8yROw",
    "_legacy_id": 48,
    "openid": "oc0ZD3aCeGoAPqR1gY4SpYo8yROw",
    "nickName": "小星",
    "avatarUrl": "https://oss-1357612648.cos.ap-shanghai.myqcloud.com/users/avatars/1775127310605_037f0e502ce9ce4f.jpg",
    "phone": "",
    "role_level": 0,
    "distributor_level": 1,
    "points": 0,
    "wallet_balance": 0,
    "referrer_openid": "oc0ZD3XxzPISJj9epmRvGrOApzQ4",
    "my_invite_code": "",
    "created_at": "2026-03-29T13:22:50.000Z",
    "updated_at": "2026-04-06T03:52:05.000Z"
  },
  {
    "_id": "oc0ZD3a5WO2RHgh6hNi2xdZO5JBw",
    "_legacy_id": 49,
    "openid": "oc0ZD3a5WO2RHgh6hNi2xdZO5JBw",
    "nickName": "Jovial",
    "avatarUrl": "https://oss-1357612648.cos.ap-shanghai.myqcloud.com/users/avatars/1774795186464_d13effeafcfe494d.jpeg",
    "phone": "",
    "role_level": 0,
    "distributor_level": 1,
    "points": 0,
    "wallet_balance": 0,
    "referrer_openid": "oc0ZD3fqS26hEFVgq0z_RzMBqCTI",
    "my_invite_code": "",
    "created_at": "2026-03-29T13:23:50.000Z",
    "updated_at": "2026-04-05T14:15:12.000Z"
  },
  {
    "_id": "oc0ZD3fwtrTApZ8JHjL00H0hXGJQ",
    "_legacy_id": 50,
    "openid": "oc0ZD3fwtrTApZ8JHjL00H0hXGJQ",
    "nickName": "爱吃月亮的猫",
    "avatarUrl": "https://oss-1357612648.cos.ap-shanghai.myqcloud.com/users/avatars/1774795075460_90ef6176b69a7841.jpg",
    "phone": "",
    "role_level": 0,
    "distributor_level": 1,
    "points": 0,
    "wallet_balance": 0,
    "referrer_openid": "oc0ZD3XxzPISJj9epmRvGrOApzQ4",
    "my_invite_code": "",
    "created_at": "2026-03-29T13:28:15.000Z",
    "updated_at": "2026-04-06T10:51:33.000Z"
  },
  {
    "_id": "oc0ZD3aMGF6IFen-1m4gdb4rYleA",
    "_legacy_id": 51,
    "openid": "oc0ZD3aMGF6IFen-1m4gdb4rYleA",
    "nickName": "园园在成长",
    "avatarUrl": "https://oss-1357612648.cos.ap-shanghai.myqcloud.com/users/avatars/1774798267387_8bfc46681bed86d9.jpeg",
    "phone": "",
    "role_level": 0,
    "distributor_level": 1,
    "points": 0,
    "wallet_balance": 0,
    "referrer_openid": "",
    "my_invite_code": "",
    "created_at": "2026-03-29T13:29:48.000Z",
    "updated_at": "2026-03-29T15:31:30.000Z"
  },
  {
    "_id": "oc0ZD3SvIQErMkhXqJxz1Kk5k2Dc",
    "_legacy_id": 52,
    "openid": "oc0ZD3SvIQErMkhXqJxz1Kk5k2Dc",
    "nickName": "嫦娥和她的老师们【学习版】",
    "avatarUrl": "https://oss-1357612648.cos.ap-shanghai.myqcloud.com/users/avatars/1774844992360_a615428aefd7303c.jpeg",
    "phone": "",
    "role_level": 0,
    "distributor_level": 1,
    "points": 0,
    "wallet_balance": 0,
    "referrer_openid": "oc0ZD3fqS26hEFVgq0z_RzMBqCTI",
    "my_invite_code": "",
    "created_at": "2026-03-29T13:31:01.000Z",
    "updated_at": "2026-04-01T13:47:51.000Z"
  },
  {
    "_id": "oc0ZD3evYUMnAPlVg6S_dbYngzn8",
    "_legacy_id": 53,
    "openid": "oc0ZD3evYUMnAPlVg6S_dbYngzn8",
    "nickName": "知水",
    "avatarUrl": "https://oss-1357612648.cos.ap-shanghai.myqcloud.com/users/avatars/1774794138157_0d97faea4a3d385f.jpeg",
    "phone": "",
    "role_level": 0,
    "distributor_level": 1,
    "points": 0,
    "wallet_balance": 0,
    "referrer_openid": "",
    "my_invite_code": "",
    "created_at": "2026-03-29T13:31:44.000Z",
    "updated_at": "2026-04-06T14:07:53.000Z"
  },
  {
    "_id": "oc0ZD3fpHk-7S7l5RQjzLhiRd830",
    "_legacy_id": 54,
    "openid": "oc0ZD3fpHk-7S7l5RQjzLhiRd830",
    "nickName": "微信用户",
    "avatarUrl": "https://oss-1357612648.cos.ap-shanghai.myqcloud.com/materials/1774767923815_dc6e31ff743275ba.jpg",
    "phone": "",
    "role_level": 0,
    "distributor_level": 1,
    "points": 0,
    "wallet_balance": 0,
    "referrer_openid": "oc0ZD3aHikFsynVAgwqQBb8ze-JQ",
    "my_invite_code": "",
    "created_at": "2026-03-29T13:32:08.000Z",
    "updated_at": "2026-03-31T08:20:37.000Z"
  },
  {
    "_id": "oc0ZD3YeYm-5rTK8k8ew-1sBubJ8",
    "_legacy_id": 55,
    "openid": "oc0ZD3YeYm-5rTK8k8ew-1sBubJ8",
    "nickName": "羽杰🌟",
    "avatarUrl": "https://oss-1357612648.cos.ap-shanghai.myqcloud.com/users/avatars/1774796172519_73e8ef00d427ba1f.jpeg",
    "phone": "",
    "role_level": 0,
    "distributor_level": 1,
    "points": 0,
    "wallet_balance": 0,
    "referrer_openid": "oc0ZD3fqS26hEFVgq0z_RzMBqCTI",
    "my_invite_code": "",
    "created_at": "2026-03-29T13:33:07.000Z",
    "updated_at": "2026-04-05T14:44:09.000Z"
  },
  {
    "_id": "oc0ZD3bYO0XafikXZptA_jhthCss",
    "_legacy_id": 56,
    "openid": "oc0ZD3bYO0XafikXZptA_jhthCss",
    "nickName": "Manxh.",
    "avatarUrl": "https://oss-1357612648.cos.ap-shanghai.myqcloud.com/users/avatars/1774802720750_34d644c03e58ba90.jpeg",
    "phone": "",
    "role_level": 0,
    "distributor_level": 1,
    "points": 0,
    "wallet_balance": 0,
    "referrer_openid": "oc0ZD3fqS26hEFVgq0z_RzMBqCTI",
    "my_invite_code": "",
    "created_at": "2026-03-29T13:35:40.000Z",
    "updated_at": "2026-03-31T06:42:19.000Z"
  },
  {
    "_id": "oc0ZD3R0JN-AEavazlkbYaQYk4wQ",
    "_legacy_id": 57,
    "openid": "oc0ZD3R0JN-AEavazlkbYaQYk4wQ",
    "nickName": "微信用户",
    "avatarUrl": "https://oss-1357612648.cos.ap-shanghai.myqcloud.com/materials/1774767923815_dc6e31ff743275ba.jpg",
    "phone": "",
    "role_level": 0,
    "distributor_level": 1,
    "points": 0,
    "wallet_balance": 0,
    "referrer_openid": "oc0ZD3XxzPISJj9epmRvGrOApzQ4",
    "my_invite_code": "",
    "created_at": "2026-03-29T13:35:49.000Z",
    "updated_at": "2026-03-29T13:35:49.000Z"
  },
  {
    "_id": "oc0ZD3S96joSqM2-jHyxZmz26m9E",
    "_legacy_id": 58,
    "openid": "oc0ZD3S96joSqM2-jHyxZmz26m9E",
    "nickName": "小文",
    "avatarUrl": "https://oss-1357612648.cos.ap-shanghai.myqcloud.com/users/avatars/1774895892307_6c1fb85b3d556750.jpeg",
    "phone": "",
    "role_level": 0,
    "distributor_level": 1,
    "points": 0,
    "wallet_balance": 0,
    "referrer_openid": "oc0ZD3fqS26hEFVgq0z_RzMBqCTI",
    "my_invite_code": "",
    "created_at": "2026-03-29T13:41:07.000Z",
    "updated_at": "2026-03-30T18:38:17.000Z"
  },
  {
    "_id": "oc0ZD3d-4Pc3985cLejRomo2P0kE",
    "_legacy_id": 59,
    "openid": "oc0ZD3d-4Pc3985cLejRomo2P0kE",
    "nickName": "万千",
    "avatarUrl": "https://oss-1357612648.cos.ap-shanghai.myqcloud.com/users/avatars/1775283390520_c70d484696bd0aad.jpeg",
    "phone": "",
    "role_level": 0,
    "distributor_level": 1,
    "points": 0,
    "wallet_balance": 0,
    "referrer_openid": "",
    "my_invite_code": "",
    "created_at": "2026-03-29T13:41:14.000Z",
    "updated_at": "2026-04-04T06:16:34.000Z"
  },
  {
    "_id": "oc0ZD3eVZQs6UvBMNo91ZVlsCKdY",
    "_legacy_id": 60,
    "openid": "oc0ZD3eVZQs6UvBMNo91ZVlsCKdY",
    "nickName": "沐白",
    "avatarUrl": "https://oss-1357612648.cos.ap-shanghai.myqcloud.com/users/avatars/1774794057604_8cf17569becdbf0b.jpg",
    "phone": "",
    "role_level": 0,
    "distributor_level": 1,
    "points": 0,
    "wallet_balance": 0,
    "referrer_openid": "oc0ZD3XxzPISJj9epmRvGrOApzQ4",
    "my_invite_code": "",
    "created_at": "2026-03-29T13:41:24.000Z",
    "updated_at": "2026-03-31T11:44:06.000Z"
  },
  {
    "_id": "oc0ZD3VR7vn20Isft8eVDUcbP1tM",
    "_legacy_id": 61,
    "openid": "oc0ZD3VR7vn20Isft8eVDUcbP1tM",
    "nickName": "微信用户",
    "avatarUrl": "https://oss-1357612648.cos.ap-shanghai.myqcloud.com/materials/1774767923815_dc6e31ff743275ba.jpg",
    "phone": "",
    "role_level": 0,
    "distributor_level": 1,
    "points": 0,
    "wallet_balance": 0,
    "referrer_openid": "",
    "my_invite_code": "",
    "created_at": "2026-03-29T13:45:01.000Z",
    "updated_at": "2026-03-29T13:50:25.000Z"
  },
  {
    "_id": "oc0ZD3aAktDHB3RGVd95Ml6_OEHA",
    "_legacy_id": 62,
    "openid": "oc0ZD3aAktDHB3RGVd95Ml6_OEHA",
    "nickName": "微信用户",
    "avatarUrl": "https://oss-1357612648.cos.ap-shanghai.myqcloud.com/materials/1774767923815_dc6e31ff743275ba.jpg",
    "phone": "",
    "role_level": 0,
    "distributor_level": 1,
    "points": 0,
    "wallet_balance": 0,
    "referrer_openid": "",
    "my_invite_code": "",
    "created_at": "2026-03-29T14:08:50.000Z",
    "updated_at": "2026-03-29T14:08:50.000Z"
  },
  {
    "_id": "oc0ZD3Z9-WNntyk2roIyMez2qkvA",
    "_legacy_id": 63,
    "openid": "oc0ZD3Z9-WNntyk2roIyMez2qkvA",
    "nickName": "微信用户",
    "avatarUrl": "https://oss-1357612648.cos.ap-shanghai.myqcloud.com/materials/1774767923815_dc6e31ff743275ba.jpg",
    "phone": "",
    "role_level": 0,
    "distributor_level": 1,
    "points": 0,
    "wallet_balance": 0,
    "referrer_openid": "",
    "my_invite_code": "",
    "created_at": "2026-03-29T14:11:36.000Z",
    "updated_at": "2026-03-29T14:11:36.000Z"
  },
  {
    "_id": "oc0ZD3dPIyMr0rILGaZOA4z_fca4",
    "_legacy_id": 64,
    "openid": "oc0ZD3dPIyMr0rILGaZOA4z_fca4",
    "nickName": "星月夜",
    "avatarUrl": "https://oss-1357612648.cos.ap-shanghai.myqcloud.com/users/avatars/1774844865925_2d0c7a91e7458f50.jpeg",
    "phone": "",
    "role_level": 0,
    "distributor_level": 1,
    "points": 0,
    "wallet_balance": 0,
    "referrer_openid": "oc0ZD3XxzPISJj9epmRvGrOApzQ4",
    "my_invite_code": "",
    "created_at": "2026-03-29T14:20:38.000Z",
    "updated_at": "2026-03-30T04:29:25.000Z"
  },
  {
    "_id": "oc0ZD3cv5f3tIuJyO_8bo3NRqi-s",
    "_legacy_id": 65,
    "openid": "oc0ZD3cv5f3tIuJyO_8bo3NRqi-s",
    "nickName": "九如",
    "avatarUrl": "https://oss-1357612648.cos.ap-shanghai.myqcloud.com/users/avatars/1774828164206_201debc8b5411937.jpeg",
    "phone": "",
    "role_level": 0,
    "distributor_level": 1,
    "points": 0,
    "wallet_balance": 0,
    "referrer_openid": "oc0ZD3XxzPISJj9epmRvGrOApzQ4",
    "my_invite_code": "",
    "created_at": "2026-03-29T14:21:17.000Z",
    "updated_at": "2026-03-29T23:49:32.000Z"
  },
  {
    "_id": "oc0ZD3cbZDrU_WwR5M6TodWOtZ8M",
    "_legacy_id": 66,
    "openid": "oc0ZD3cbZDrU_WwR5M6TodWOtZ8M",
    "nickName": "司宇",
    "avatarUrl": "https://oss-1357612648.cos.ap-shanghai.myqcloud.com/users/avatars/1774795083170_9f4c0697eeadc79f.jpeg",
    "phone": "",
    "role_level": 0,
    "distributor_level": 1,
    "points": 0,
    "wallet_balance": 0,
    "referrer_openid": "",
    "my_invite_code": "",
    "created_at": "2026-03-29T14:24:45.000Z",
    "updated_at": "2026-03-29T14:38:57.000Z"
  },
  {
    "_id": "oc0ZD3T_N75ZhwqWpPNF1MVr7vfE",
    "_legacy_id": 67,
    "openid": "oc0ZD3T_N75ZhwqWpPNF1MVr7vfE",
    "nickName": "满庭芳",
    "avatarUrl": "https://oss-1357612648.cos.ap-shanghai.myqcloud.com/users/avatars/1774794506692_31be136897624a2e.jpeg",
    "phone": "",
    "role_level": 0,
    "distributor_level": 1,
    "points": 0,
    "wallet_balance": 0,
    "referrer_openid": "oc0ZD3XxzPISJj9epmRvGrOApzQ4",
    "my_invite_code": "",
    "created_at": "2026-03-29T14:28:11.000Z",
    "updated_at": "2026-04-05T14:36:13.000Z"
  },
  {
    "_id": "oc0ZD3Q2Jxw1hlVdtK88Nk3irkKs",
    "_legacy_id": 68,
    "openid": "oc0ZD3Q2Jxw1hlVdtK88Nk3irkKs",
    "nickName": "梦想家逸帆",
    "avatarUrl": "https://oss-1357612648.cos.ap-shanghai.myqcloud.com/users/avatars/1774794816959_24889efe50d46e6d.jpeg",
    "phone": "",
    "role_level": 0,
    "distributor_level": 1,
    "points": 0,
    "wallet_balance": 0,
    "referrer_openid": "oc0ZD3XxzPISJj9epmRvGrOApzQ4",
    "my_invite_code": "",
    "created_at": "2026-03-29T14:33:27.000Z",
    "updated_at": "2026-03-29T14:33:43.000Z"
  },
  {
    "_id": "oc0ZD3TYslU9Vw91bdIhtQRnVAQ0",
    "_legacy_id": 69,
    "openid": "oc0ZD3TYslU9Vw91bdIhtQRnVAQ0",
    "nickName": "星星向荣",
    "avatarUrl": "https://oss-1357612648.cos.ap-shanghai.myqcloud.com/users/avatars/1774868523149_edad312dd4c95064.jpeg",
    "phone": "",
    "role_level": 0,
    "distributor_level": 1,
    "points": 0,
    "wallet_balance": 0,
    "referrer_openid": "",
    "my_invite_code": "",
    "created_at": "2026-03-29T14:38:16.000Z",
    "updated_at": "2026-03-30T11:02:07.000Z"
  },
  {
    "_id": "oc0ZD3XNpvPj9tJp3mwYdjWWDi3I",
    "_legacy_id": 70,
    "openid": "oc0ZD3XNpvPj9tJp3mwYdjWWDi3I",
    "nickName": "妤🍭",
    "avatarUrl": "https://oss-1357612648.cos.ap-shanghai.myqcloud.com/users/avatars/1774845203405_9c5133874fe28a03.jpeg",
    "phone": "",
    "role_level": 0,
    "distributor_level": 1,
    "points": 0,
    "wallet_balance": 0,
    "referrer_openid": "oc0ZD3Y5yrF5ezpwwSPUtkJWna1Q",
    "my_invite_code": "",
    "created_at": "2026-03-29T14:38:50.000Z",
    "updated_at": "2026-03-30T15:46:44.000Z"
  },
  {
    "_id": "oc0ZD3dZzQd6dzsIFLypuRr4j5u0",
    "_legacy_id": 71,
    "openid": "oc0ZD3dZzQd6dzsIFLypuRr4j5u0",
    "nickName": "小安和他的朋友们",
    "avatarUrl": "https://oss-1357612648.cos.ap-shanghai.myqcloud.com/users/avatars/1774795410177_91f03e485799c9b4.jpeg",
    "phone": "",
    "role_level": 0,
    "distributor_level": 1,
    "points": 0,
    "wallet_balance": 0,
    "referrer_openid": "",
    "my_invite_code": "",
    "created_at": "2026-03-29T14:39:56.000Z",
    "updated_at": "2026-03-29T14:43:39.000Z"
  },
  {
    "_id": "oc0ZD3UqFSQhMJbOyI0OQomHwd44",
    "_legacy_id": 72,
    "openid": "oc0ZD3UqFSQhMJbOyI0OQomHwd44",
    "nickName": "微信用户",
    "avatarUrl": "https://oss-1357612648.cos.ap-shanghai.myqcloud.com/materials/1774767923815_dc6e31ff743275ba.jpg",
    "phone": "",
    "role_level": 0,
    "distributor_level": 1,
    "points": 0,
    "wallet_balance": 0,
    "referrer_openid": "",
    "my_invite_code": "",
    "created_at": "2026-03-29T14:40:56.000Z",
    "updated_at": "2026-03-29T14:40:56.000Z"
  },
  {
    "_id": "oc0ZD3X_m_pBsMwpQn57uZmBRai4",
    "_legacy_id": 73,
    "openid": "oc0ZD3X_m_pBsMwpQn57uZmBRai4",
    "nickName": "梅大王🌸",
    "avatarUrl": "https://oss-1357612648.cos.ap-shanghai.myqcloud.com/users/avatars/1774795667084_13f0886a10789485.jpg",
    "phone": "",
    "role_level": 0,
    "distributor_level": 1,
    "points": 0,
    "wallet_balance": 0,
    "referrer_openid": "",
    "my_invite_code": "",
    "created_at": "2026-03-29T14:45:23.000Z",
    "updated_at": "2026-03-29T14:49:18.000Z"
  },
  {
    "_id": "oc0ZD3YQPEkhv6Q37ZdtBFBjWerA",
    "_legacy_id": 74,
    "openid": "oc0ZD3YQPEkhv6Q37ZdtBFBjWerA",
    "nickName": "江橙🍊和他的老师们",
    "avatarUrl": "https://oss-1357612648.cos.ap-shanghai.myqcloud.com/users/avatars/1774796766024_a40c7bceb611281c.jpeg",
    "phone": "",
    "role_level": 0,
    "distributor_level": 1,
    "points": 0,
    "wallet_balance": 0,
    "referrer_openid": "oc0ZD3evYUMnAPlVg6S_dbYngzn8",
    "my_invite_code": "",
    "created_at": "2026-03-29T15:02:55.000Z",
    "updated_at": "2026-03-30T04:51:00.000Z"
  },
  {
    "_id": "oc0ZD3RH90ZZ5u00tpzkKV2iqS88",
    "_legacy_id": 75,
    "openid": "oc0ZD3RH90ZZ5u00tpzkKV2iqS88",
    "nickName": "微信用户",
    "avatarUrl": "https://oss-1357612648.cos.ap-shanghai.myqcloud.com/materials/1774767923815_dc6e31ff743275ba.jpg",
    "phone": "",
    "role_level": 0,
    "distributor_level": 1,
    "points": 0,
    "wallet_balance": 0,
    "referrer_openid": "oc0ZD3evYUMnAPlVg6S_dbYngzn8",
    "my_invite_code": "",
    "created_at": "2026-03-29T15:03:10.000Z",
    "updated_at": "2026-03-30T04:50:52.000Z"
  },
  {
    "_id": "oc0ZD3TUdKdXXUoEI7CEMO41fHxs",
    "_legacy_id": 76,
    "openid": "oc0ZD3TUdKdXXUoEI7CEMO41fHxs",
    "nickName": "狐狸",
    "avatarUrl": "https://oss-1357612648.cos.ap-shanghai.myqcloud.com/users/avatars/1774798862562_a03d86d0c8364999.jpeg",
    "phone": "",
    "role_level": 0,
    "distributor_level": 1,
    "points": 0,
    "wallet_balance": 0,
    "referrer_openid": "oc0ZD3aMGF6IFen-1m4gdb4rYleA",
    "my_invite_code": "",
    "created_at": "2026-03-29T15:24:38.000Z",
    "updated_at": "2026-04-01T00:28:50.000Z"
  },
  {
    "_id": "oc0ZD3SFv6AMvU5LKYbe2HDuKdg0",
    "_legacy_id": 77,
    "openid": "oc0ZD3SFv6AMvU5LKYbe2HDuKdg0",
    "nickName": "李玲玲",
    "avatarUrl": "https://oss-1357612648.cos.ap-shanghai.myqcloud.com/users/avatars/1775473250455_0f7e503b2bf36f21.jpeg",
    "phone": "",
    "role_level": 0,
    "distributor_level": 1,
    "points": 0,
    "wallet_balance": 0,
    "referrer_openid": "oc0ZD3fwtrTApZ8JHjL00H0hXGJQ",
    "my_invite_code": "",
    "created_at": "2026-03-29T15:34:15.000Z",
    "updated_at": "2026-04-06T11:00:56.000Z"
  },
  {
    "_id": "oc0ZD3cWenUCs1iFHi5rWylk1rpQ",
    "_legacy_id": 78,
    "openid": "oc0ZD3cWenUCs1iFHi5rWylk1rpQ",
    "nickName": "晒晒晒太阳",
    "avatarUrl": "https://oss-1357612648.cos.ap-shanghai.myqcloud.com/users/avatars/1774869206357_a5183f6ba40192f2.jpeg",
    "phone": "",
    "role_level": 0,
    "distributor_level": 1,
    "points": 0,
    "wallet_balance": 0,
    "referrer_openid": "oc0ZD3fqS26hEFVgq0z_RzMBqCTI",
    "my_invite_code": "",
    "created_at": "2026-03-29T17:18:57.000Z",
    "updated_at": "2026-04-06T08:53:41.000Z"
  },
  {
    "_id": "oc0ZD3XSX5ZoTpG21QUrcWVipLj8",
    "_legacy_id": 79,
    "openid": "oc0ZD3XSX5ZoTpG21QUrcWVipLj8",
    "nickName": "万木成行",
    "avatarUrl": "https://oss-1357612648.cos.ap-shanghai.myqcloud.com/users/avatars/1774844934155_36754a71df3ac7a4.jpeg",
    "phone": "",
    "role_level": 0,
    "distributor_level": 1,
    "points": 0,
    "wallet_balance": 0,
    "referrer_openid": "oc0ZD3fqS26hEFVgq0z_RzMBqCTI",
    "my_invite_code": "",
    "created_at": "2026-03-29T23:27:48.000Z",
    "updated_at": "2026-04-04T05:10:29.000Z"
  },
  {
    "_id": "oc0ZD3ZcMHTha7vRYD14aN1Jg8yw",
    "_legacy_id": 80,
    "openid": "oc0ZD3ZcMHTha7vRYD14aN1Jg8yw",
    "nickName": "微信用户",
    "avatarUrl": "https://oss-1357612648.cos.ap-shanghai.myqcloud.com/materials/1774767923815_dc6e31ff743275ba.jpg",
    "phone": "",
    "role_level": 0,
    "distributor_level": 1,
    "points": 0,
    "wallet_balance": 0,
    "referrer_openid": "oc0ZD3fqS26hEFVgq0z_RzMBqCTI",
    "my_invite_code": "",
    "created_at": "2026-03-29T23:46:59.000Z",
    "updated_at": "2026-04-06T06:42:51.000Z"
  },
  {
    "_id": "oc0ZD3RfHAhTtvIt9ICNnCBS6mY4",
    "_legacy_id": 81,
    "openid": "oc0ZD3RfHAhTtvIt9ICNnCBS6mY4",
    "nickName": "二分之蓝",
    "avatarUrl": "https://oss-1357612648.cos.ap-shanghai.myqcloud.com/users/avatars/1774828477330_ef26fd4231aaf525.jpeg",
    "phone": "",
    "role_level": 0,
    "distributor_level": 1,
    "points": 0,
    "wallet_balance": 0,
    "referrer_openid": "oc0ZD3fqS26hEFVgq0z_RzMBqCTI",
    "my_invite_code": "",
    "created_at": "2026-03-29T23:52:07.000Z",
    "updated_at": "2026-03-30T11:29:02.000Z"
  },
  {
    "_id": "oc0ZD3ZOWRZekk2rLlJo-9RzVS-w",
    "_legacy_id": 82,
    "openid": "oc0ZD3ZOWRZekk2rLlJo-9RzVS-w",
    "nickName": "Go!",
    "avatarUrl": "https://oss-1357612648.cos.ap-shanghai.myqcloud.com/users/avatars/1774828992306_bc983230a7da457d.jpeg",
    "phone": "",
    "role_level": 0,
    "distributor_level": 1,
    "points": 0,
    "wallet_balance": 0,
    "referrer_openid": "",
    "my_invite_code": "",
    "created_at": "2026-03-29T23:57:48.000Z",
    "updated_at": "2026-03-30T00:03:22.000Z"
  },
  {
    "_id": "oc0ZD3Ub6fKomw_oWA_vG8PtcQUc",
    "_legacy_id": 83,
    "openid": "oc0ZD3Ub6fKomw_oWA_vG8PtcQUc",
    "nickName": "何妨",
    "avatarUrl": "https://oss-1357612648.cos.ap-shanghai.myqcloud.com/users/avatars/1774829967708_c9ead6c100156e7a.jpeg",
    "phone": "",
    "role_level": 0,
    "distributor_level": 1,
    "points": 0,
    "wallet_balance": 0,
    "referrer_openid": "",
    "my_invite_code": "",
    "created_at": "2026-03-30T00:18:29.000Z",
    "updated_at": "2026-03-30T13:14:46.000Z"
  },
  {
    "_id": "oc0ZD3Vq6_rfZZGh-bDuiiSQse24",
    "_legacy_id": 84,
    "openid": "oc0ZD3Vq6_rfZZGh-bDuiiSQse24",
    "nickName": "曦",
    "avatarUrl": "https://oss-1357612648.cos.ap-shanghai.myqcloud.com/users/avatars/1774868803229_2d71b04bea06f150.jpeg",
    "phone": "",
    "role_level": 0,
    "distributor_level": 1,
    "points": 0,
    "wallet_balance": 0,
    "referrer_openid": "",
    "my_invite_code": "",
    "created_at": "2026-03-30T01:59:38.000Z",
    "updated_at": "2026-03-30T11:06:46.000Z"
  },
  {
    "_id": "oc0ZD3bxDk2c8SmgkgAteTdOVvIU",
    "_legacy_id": 85,
    "openid": "oc0ZD3bxDk2c8SmgkgAteTdOVvIU",
    "nickName": "微信用户",
    "avatarUrl": "/assets/images/default-avatar.svg",
    "phone": "",
    "role_level": 0,
    "distributor_level": 1,
    "points": 0,
    "wallet_balance": 0,
    "referrer_openid": "oc0ZD3fwtrTApZ8JHjL00H0hXGJQ",
    "my_invite_code": "",
    "created_at": "2026-03-30T02:59:28.000Z",
    "updated_at": "2026-03-30T03:41:42.000Z"
  },
  {
    "_id": "oc0ZD3ePZaZuXrFoxnrRnvN2trRg",
    "_legacy_id": 86,
    "openid": "oc0ZD3ePZaZuXrFoxnrRnvN2trRg",
    "nickName": "wxid_vw5s67h5khhp12",
    "avatarUrl": "https://oss-1357612648.cos.ap-shanghai.myqcloud.com/users/avatars/1774840629127_788ddcbb9e4b3578.png",
    "phone": "",
    "role_level": 0,
    "distributor_level": 1,
    "points": 0,
    "wallet_balance": 0,
    "referrer_openid": "",
    "my_invite_code": "",
    "created_at": "2026-03-30T03:12:25.000Z",
    "updated_at": "2026-03-30T03:17:09.000Z"
  },
  {
    "_id": "oc0ZD3cqq6s1xq6cRfSwk16IQXz8",
    "_legacy_id": 87,
    "openid": "oc0ZD3cqq6s1xq6cRfSwk16IQXz8",
    "nickName": "次旦普尺",
    "avatarUrl": "https://oss-1357612648.cos.ap-shanghai.myqcloud.com/users/avatars/1774844637843_84458aa13f36c211.jpeg",
    "phone": "",
    "role_level": 0,
    "distributor_level": 1,
    "points": 0,
    "wallet_balance": 0,
    "referrer_openid": "oc0ZD3XxzPISJj9epmRvGrOApzQ4",
    "my_invite_code": "",
    "created_at": "2026-03-30T04:23:45.000Z",
    "updated_at": "2026-03-30T04:24:02.000Z"
  },
  {
    "_id": "oc0ZD3fS6XByeBbincx24REuIanQ",
    "_legacy_id": 88,
    "openid": "oc0ZD3fS6XByeBbincx24REuIanQ",
    "nickName": "未熵",
    "avatarUrl": "https://oss-1357612648.cos.ap-shanghai.myqcloud.com/users/avatars/1774844632097_c430d95bbc97637e.jpeg",
    "phone": "",
    "role_level": 0,
    "distributor_level": 1,
    "points": 0,
    "wallet_balance": 0,
    "referrer_openid": "oc0ZD3XxzPISJj9epmRvGrOApzQ4",
    "my_invite_code": "",
    "created_at": "2026-03-30T04:23:45.000Z",
    "updated_at": "2026-03-30T04:45:22.000Z"
  },
  {
    "_id": "oc0ZD3SdMkbM0p0FJ9Fh3rAcoo1Q",
    "_legacy_id": 89,
    "openid": "oc0ZD3SdMkbM0p0FJ9Fh3rAcoo1Q",
    "nickName": "微信用户",
    "avatarUrl": "/assets/images/default-avatar.svg",
    "phone": "",
    "role_level": 0,
    "distributor_level": 1,
    "points": 0,
    "wallet_balance": 0,
    "referrer_openid": "oc0ZD3fS6XByeBbincx24REuIanQ",
    "my_invite_code": "",
    "created_at": "2026-03-30T04:25:37.000Z",
    "updated_at": "2026-03-30T04:25:37.000Z"
  },
  {
    "_id": "oc0ZD3fOVsPDOPEcZ4tgB1nIxVRw",
    "_legacy_id": 90,
    "openid": "oc0ZD3fOVsPDOPEcZ4tgB1nIxVRw",
    "nickName": "微信用户",
    "avatarUrl": "/assets/images/default-avatar.svg",
    "phone": "",
    "role_level": 0,
    "distributor_level": 1,
    "points": 0,
    "wallet_balance": 0,
    "referrer_openid": "oc0ZD3fS6XByeBbincx24REuIanQ",
    "my_invite_code": "",
    "created_at": "2026-03-30T04:45:22.000Z",
    "updated_at": "2026-03-30T04:45:27.000Z"
  },
  {
    "_id": "oc0ZD3RNUghaR5DBFx3PYG6UjyO0",
    "_legacy_id": 91,
    "openid": "oc0ZD3RNUghaR5DBFx3PYG6UjyO0",
    "nickName": "CiCi",
    "avatarUrl": "https://oss-1357612648.cos.ap-shanghai.myqcloud.com/users/avatars/1774845996917_13cef91eb97acf53.jpg",
    "phone": "",
    "role_level": 0,
    "distributor_level": 1,
    "points": 0,
    "wallet_balance": 0,
    "referrer_openid": "oc0ZD3evYUMnAPlVg6S_dbYngzn8",
    "my_invite_code": "",
    "created_at": "2026-03-30T04:45:54.000Z",
    "updated_at": "2026-03-30T04:48:08.000Z"
  },
  {
    "_id": "oc0ZD3e3PcxflFDaEsR3b-KCAfeM",
    "_legacy_id": 92,
    "openid": "oc0ZD3e3PcxflFDaEsR3b-KCAfeM",
    "nickName": "微信用户",
    "avatarUrl": "/assets/images/default-avatar.svg",
    "phone": "",
    "role_level": 0,
    "distributor_level": 1,
    "points": 0,
    "wallet_balance": 0,
    "referrer_openid": "oc0ZD3evYUMnAPlVg6S_dbYngzn8",
    "my_invite_code": "",
    "created_at": "2026-03-30T04:51:09.000Z",
    "updated_at": "2026-03-30T04:51:09.000Z"
  },
  {
    "_id": "oc0ZD3dqIyICo0ZATsyJ_51_kjik",
    "_legacy_id": 93,
    "openid": "oc0ZD3dqIyICo0ZATsyJ_51_kjik",
    "nickName": "微信用户",
    "avatarUrl": "/assets/images/default-avatar.svg",
    "phone": "",
    "role_level": 0,
    "distributor_level": 1,
    "points": 1,
    "wallet_balance": 0,
    "referrer_openid": "oc0ZD3evYUMnAPlVg6S_dbYngzn8",
    "my_invite_code": "",
    "created_at": "2026-03-30T04:51:10.000Z",
    "updated_at": "2026-03-30T04:55:49.000Z"
  },
  {
    "_id": "oc0ZD3UojAOb02UViNsZuaEVITkM",
    "_legacy_id": 94,
    "openid": "oc0ZD3UojAOb02UViNsZuaEVITkM",
    "nickName": "小焰",
    "avatarUrl": "https://oss-1357612648.cos.ap-shanghai.myqcloud.com/users/avatars/1774846594217_579a09f0b990b544.jpg",
    "phone": "",
    "role_level": 0,
    "distributor_level": 1,
    "points": 0,
    "wallet_balance": 0,
    "referrer_openid": "oc0ZD3evYUMnAPlVg6S_dbYngzn8",
    "my_invite_code": "",
    "created_at": "2026-03-30T04:55:38.000Z",
    "updated_at": "2026-03-31T07:48:00.000Z"
  },
  {
    "_id": "oc0ZD3RSM8s5nrRVgCdn14AiVqv4",
    "_legacy_id": 95,
    "openid": "oc0ZD3RSM8s5nrRVgCdn14AiVqv4",
    "nickName": "微信用户",
    "avatarUrl": "https://oss-1357612648.cos.ap-shanghai.myqcloud.com/users/avatars/1774874643466_69b81b51724da690.jpeg",
    "phone": "",
    "role_level": 0,
    "distributor_level": 1,
    "points": 0,
    "wallet_balance": 0,
    "referrer_openid": "oc0ZD3evYUMnAPlVg6S_dbYngzn8",
    "my_invite_code": "",
    "created_at": "2026-03-30T05:00:32.000Z",
    "updated_at": "2026-03-30T13:28:17.000Z"
  },
  {
    "_id": "oc0ZD3VWZqlLJo3DWn0CHjWny84Y",
    "_legacy_id": 96,
    "openid": "oc0ZD3VWZqlLJo3DWn0CHjWny84Y",
    "nickName": "微信用户",
    "avatarUrl": "/assets/images/default-avatar.svg",
    "phone": "",
    "role_level": 0,
    "distributor_level": 1,
    "points": 0,
    "wallet_balance": 0,
    "referrer_openid": "oc0ZD3fqS26hEFVgq0z_RzMBqCTI",
    "my_invite_code": "",
    "created_at": "2026-03-30T05:16:19.000Z",
    "updated_at": "2026-03-30T05:16:19.000Z"
  },
  {
    "_id": "oc0ZD3fwIvP8_1IceOTdtE-jxGgU",
    "_legacy_id": 97,
    "openid": "oc0ZD3fwIvP8_1IceOTdtE-jxGgU",
    "nickName": "微信用户",
    "avatarUrl": "/assets/images/default-avatar.svg",
    "phone": "",
    "role_level": 0,
    "distributor_level": 1,
    "points": 0,
    "wallet_balance": 0,
    "referrer_openid": "",
    "my_invite_code": "",
    "created_at": "2026-03-30T05:29:59.000Z",
    "updated_at": "2026-04-01T07:30:24.000Z"
  },
  {
    "_id": "oc0ZD3drL5xUDUKTqleMP4ksa-os",
    "_legacy_id": 98,
    "openid": "oc0ZD3drL5xUDUKTqleMP4ksa-os",
    "nickName": "微信用户",
    "avatarUrl": "/assets/images/default-avatar.svg",
    "phone": "",
    "role_level": 0,
    "distributor_level": 1,
    "points": 0,
    "wallet_balance": 0,
    "referrer_openid": "oc0ZD3XxzPISJj9epmRvGrOApzQ4",
    "my_invite_code": "",
    "created_at": "2026-03-30T05:40:23.000Z",
    "updated_at": "2026-03-30T05:40:24.000Z"
  },
  {
    "_id": "oc0ZD3UGt-nqD0_R8ozFY56gtVaw",
    "_legacy_id": 99,
    "openid": "oc0ZD3UGt-nqD0_R8ozFY56gtVaw",
    "nickName": "刘祐祎（yī）",
    "avatarUrl": "https://oss-1357612648.cos.ap-shanghai.myqcloud.com/users/avatars/1774849792572_d81f009869a36905.jpeg",
    "phone": "",
    "role_level": 0,
    "distributor_level": 1,
    "points": 0,
    "wallet_balance": 0,
    "referrer_openid": "oc0ZD3fqS26hEFVgq0z_RzMBqCTI",
    "my_invite_code": "",
    "created_at": "2026-03-30T05:47:05.000Z",
    "updated_at": "2026-03-30T05:50:30.000Z"
  },
  {
    "_id": "oc0ZD3VLuc-ERfay4PVJ7XnekR2Y",
    "_legacy_id": 100,
    "openid": "oc0ZD3VLuc-ERfay4PVJ7XnekR2Y",
    "nickName": "政权和他的老师们",
    "avatarUrl": "https://oss-1357612648.cos.ap-shanghai.myqcloud.com/users/avatars/1774851728651_cd116c8e29fcff4d.jpeg",
    "phone": "",
    "role_level": 0,
    "distributor_level": 1,
    "points": 0,
    "wallet_balance": 0,
    "referrer_openid": "oc0ZD3XxzPISJj9epmRvGrOApzQ4",
    "my_invite_code": "",
    "created_at": "2026-03-30T06:21:07.000Z",
    "updated_at": "2026-03-30T06:22:14.000Z"
  },
  {
    "_id": "oc0ZD3SNDcRYX7JudJTv4ZyH7i9E",
    "_legacy_id": 101,
    "openid": "oc0ZD3SNDcRYX7JudJTv4ZyH7i9E",
    "nickName": "微信用户",
    "avatarUrl": "/assets/images/default-avatar.svg",
    "phone": "",
    "role_level": 0,
    "distributor_level": 1,
    "points": 0,
    "wallet_balance": 0,
    "referrer_openid": "",
    "my_invite_code": "",
    "created_at": "2026-03-30T07:06:50.000Z",
    "updated_at": "2026-03-30T07:06:50.000Z"
  },
  {
    "_id": "oc0ZD3WzclTNsa96DtDnY8wyoNM8",
    "_legacy_id": 102,
    "openid": "oc0ZD3WzclTNsa96DtDnY8wyoNM8",
    "nickName": "Sein zum Tode",
    "avatarUrl": "https://oss-1357612648.cos.ap-shanghai.myqcloud.com/users/avatars/1774855524079_fad854690de282ac.jpeg",
    "phone": "",
    "role_level": 0,
    "distributor_level": 1,
    "points": 0,
    "wallet_balance": 0,
    "referrer_openid": "oc0ZD3fqS26hEFVgq0z_RzMBqCTI",
    "my_invite_code": "",
    "created_at": "2026-03-30T07:18:53.000Z",
    "updated_at": "2026-03-30T07:25:27.000Z"
  },
  {
    "_id": "oc0ZD3VTKxBlvH1PIilOFSD1VU7c",
    "_legacy_id": 103,
    "openid": "oc0ZD3VTKxBlvH1PIilOFSD1VU7c",
    "nickName": "Sun",
    "avatarUrl": "https://oss-1357612648.cos.ap-shanghai.myqcloud.com/users/avatars/1774856163695_d616f798cd1f6e62.jpeg",
    "phone": "",
    "role_level": 0,
    "distributor_level": 1,
    "points": 0,
    "wallet_balance": 0,
    "referrer_openid": "oc0ZD3fqS26hEFVgq0z_RzMBqCTI",
    "my_invite_code": "",
    "created_at": "2026-03-30T07:32:11.000Z",
    "updated_at": "2026-04-07T02:55:02.000Z"
  },
  {
    "_id": "oc0ZD3fxLlh2KrR7-iOFgEEr6gns",
    "_legacy_id": 104,
    "openid": "oc0ZD3fxLlh2KrR7-iOFgEEr6gns",
    "nickName": "贩售云朵",
    "avatarUrl": "https://oss-1357612648.cos.ap-shanghai.myqcloud.com/users/avatars/1774858445140_6468420527e8e534.jpg",
    "phone": "",
    "role_level": 0,
    "distributor_level": 1,
    "points": 0,
    "wallet_balance": 0,
    "referrer_openid": "oc0ZD3XxzPISJj9epmRvGrOApzQ4",
    "my_invite_code": "",
    "created_at": "2026-03-30T08:08:55.000Z",
    "updated_at": "2026-03-30T08:14:26.000Z"
  },
  {
    "_id": "oc0ZD3U82G0xr53gxoxTiITj13xQ",
    "_legacy_id": 105,
    "openid": "oc0ZD3U82G0xr53gxoxTiITj13xQ",
    "nickName": "叶岩·ROC",
    "avatarUrl": "https://oss-1357612648.cos.ap-shanghai.myqcloud.com/users/avatars/1774871244670_4e409d74c3147384.jpeg",
    "phone": "",
    "role_level": 0,
    "distributor_level": 1,
    "points": 0,
    "wallet_balance": 0,
    "referrer_openid": "oc0ZD3VTKxBlvH1PIilOFSD1VU7c",
    "my_invite_code": "",
    "created_at": "2026-03-30T08:24:12.000Z",
    "updated_at": "2026-04-07T02:55:02.000Z"
  },
  {
    "_id": "oc0ZD3ZLcg1rTsl2I164M-PvHtpQ",
    "_legacy_id": 106,
    "openid": "oc0ZD3ZLcg1rTsl2I164M-PvHtpQ",
    "nickName": "小奥",
    "avatarUrl": "https://oss-1357612648.cos.ap-shanghai.myqcloud.com/users/avatars/1774860379024_9baf4be9d5feeba6.jpg",
    "phone": "",
    "role_level": 0,
    "distributor_level": 1,
    "points": 0,
    "wallet_balance": 0,
    "referrer_openid": "",
    "my_invite_code": "",
    "created_at": "2026-03-30T08:43:35.000Z",
    "updated_at": "2026-03-30T08:46:19.000Z"
  },
  {
    "_id": "oc0ZD3b0yIUHEvStN0BZPUXpezng",
    "_legacy_id": 107,
    "openid": "oc0ZD3b0yIUHEvStN0BZPUXpezng",
    "nickName": "用户78158611",
    "avatarUrl": "https://oss-1357612648.cos.ap-shanghai.myqcloud.com/users/avatars/1774860615260_76c6854fdcabfec4.jpeg",
    "phone": "",
    "role_level": 0,
    "distributor_level": 1,
    "points": 0,
    "wallet_balance": 0,
    "referrer_openid": "oc0ZD3fqS26hEFVgq0z_RzMBqCTI",
    "my_invite_code": "",
    "created_at": "2026-03-30T08:47:27.000Z",
    "updated_at": "2026-03-30T11:12:29.000Z"
  },
  {
    "_id": "oc0ZD3YpHJvUxAK79fMjRKVlrvhk",
    "_legacy_id": 108,
    "openid": "oc0ZD3YpHJvUxAK79fMjRKVlrvhk",
    "nickName": "颖火虫",
    "avatarUrl": "https://oss-1357612648.cos.ap-shanghai.myqcloud.com/users/avatars/1774860872183_88994f3c095973c0.jpeg",
    "phone": "",
    "role_level": 0,
    "distributor_level": 1,
    "points": 0,
    "wallet_balance": 0,
    "referrer_openid": "oc0ZD3evYUMnAPlVg6S_dbYngzn8",
    "my_invite_code": "",
    "created_at": "2026-03-30T08:54:10.000Z",
    "updated_at": "2026-03-30T13:15:53.000Z"
  },
  {
    "_id": "oc0ZD3bUbNTkDvkFcHmMZ_2oDe9w",
    "_legacy_id": 109,
    "openid": "oc0ZD3bUbNTkDvkFcHmMZ_2oDe9w",
    "nickName": "微信用户",
    "avatarUrl": "/assets/images/default-avatar.svg",
    "phone": "",
    "role_level": 0,
    "distributor_level": 1,
    "points": 0,
    "wallet_balance": 0,
    "referrer_openid": "oc0ZD3fwtrTApZ8JHjL00H0hXGJQ",
    "my_invite_code": "",
    "created_at": "2026-03-30T10:15:29.000Z",
    "updated_at": "2026-03-30T10:15:29.000Z"
  },
  {
    "_id": "oc0ZD3Z0xk7vEcILzHqzU6X6Ho48",
    "_legacy_id": 110,
    "openid": "oc0ZD3Z0xk7vEcILzHqzU6X6Ho48",
    "nickName": "傲娇大小姐",
    "avatarUrl": "https://oss-1357612648.cos.ap-shanghai.myqcloud.com/users/avatars/1774868506784_ce7a3a75fba0c1fb.jpg",
    "phone": "",
    "role_level": 0,
    "distributor_level": 1,
    "points": 0,
    "wallet_balance": 0,
    "referrer_openid": "oc0ZD3U82G0xr53gxoxTiITj13xQ",
    "my_invite_code": "",
    "created_at": "2026-03-30T11:01:24.000Z",
    "updated_at": "2026-03-30T11:04:00.000Z"
  },
  {
    "_id": "oc0ZD3RfNof56Xx4iQeOWOVbwRdc",
    "_legacy_id": 111,
    "openid": "oc0ZD3RfNof56Xx4iQeOWOVbwRdc",
    "nickName": "燚垚（原梦想）",
    "avatarUrl": "https://oss-1357612648.cos.ap-shanghai.myqcloud.com/users/avatars/1774868584402_7f0072b9b834449b.jpeg",
    "phone": "",
    "role_level": 0,
    "distributor_level": 1,
    "points": 0,
    "wallet_balance": 0,
    "referrer_openid": "oc0ZD3evYUMnAPlVg6S_dbYngzn8",
    "my_invite_code": "",
    "created_at": "2026-03-30T11:02:39.000Z",
    "updated_at": "2026-03-30T11:03:56.000Z"
  },
  {
    "_id": "oc0ZD3Yi5V8YvqY8YMEQKasPTktg",
    "_legacy_id": 112,
    "openid": "oc0ZD3Yi5V8YvqY8YMEQKasPTktg",
    "nickName": "wxid_ahah4ny72dhv12",
    "avatarUrl": "https://oss-1357612648.cos.ap-shanghai.myqcloud.com/users/avatars/1774868960052_33ed6517844973ff.png",
    "phone": "",
    "role_level": 0,
    "distributor_level": 1,
    "points": 0,
    "wallet_balance": 0,
    "referrer_openid": "",
    "my_invite_code": "",
    "created_at": "2026-03-30T11:05:46.000Z",
    "updated_at": "2026-03-30T11:10:37.000Z"
  },
  {
    "_id": "oc0ZD3cwCDgiDtSJSV_-8x7f6H3Q",
    "_legacy_id": 113,
    "openid": "oc0ZD3cwCDgiDtSJSV_-8x7f6H3Q",
    "nickName": "雪珂",
    "avatarUrl": "https://oss-1357612648.cos.ap-shanghai.myqcloud.com/users/avatars/1774870408925_406634ca839e689d.jpeg",
    "phone": "",
    "role_level": 0,
    "distributor_level": 1,
    "points": 0,
    "wallet_balance": 0,
    "referrer_openid": "",
    "my_invite_code": "",
    "created_at": "2026-03-30T11:33:17.000Z",
    "updated_at": "2026-04-06T12:52:24.000Z"
  },
  {
    "_id": "oc0ZD3TBO08NCQKnUjqdwZj_vo0M",
    "_legacy_id": 114,
    "openid": "oc0ZD3TBO08NCQKnUjqdwZj_vo0M",
    "nickName": "He Ts",
    "avatarUrl": "https://oss-1357612648.cos.ap-shanghai.myqcloud.com/users/avatars/1774871095230_69bf4eb9161f056b.jpeg",
    "phone": "",
    "role_level": 0,
    "distributor_level": 1,
    "points": 0,
    "wallet_balance": 0,
    "referrer_openid": "oc0ZD3YpHJvUxAK79fMjRKVlrvhk",
    "my_invite_code": "",
    "created_at": "2026-03-30T11:44:45.000Z",
    "updated_at": "2026-03-30T11:44:59.000Z"
  },
  {
    "_id": "oc0ZD3asWXBysrePxyRn63vkFxJk",
    "_legacy_id": 115,
    "openid": "oc0ZD3asWXBysrePxyRn63vkFxJk",
    "nickName": "小米",
    "avatarUrl": "https://oss-1357612648.cos.ap-shanghai.myqcloud.com/users/avatars/1774874773126_755c74b9d4ed63d2.jpg",
    "phone": "",
    "role_level": 0,
    "distributor_level": 1,
    "points": 0,
    "wallet_balance": 0,
    "referrer_openid": "oc0ZD3aHikFsynVAgwqQBb8ze-JQ",
    "my_invite_code": "",
    "created_at": "2026-03-30T12:28:21.000Z",
    "updated_at": "2026-03-30T12:46:19.000Z"
  },
  {
    "_id": "oc0ZD3V4iM7Qk1EC0em2cTozRfUI",
    "_legacy_id": 116,
    "openid": "oc0ZD3V4iM7Qk1EC0em2cTozRfUI",
    "nickName": "浮却",
    "avatarUrl": "https://oss-1357612648.cos.ap-shanghai.myqcloud.com/users/avatars/1774876058162_f933b42d4fa04814.jpeg",
    "phone": "",
    "role_level": 0,
    "distributor_level": 1,
    "points": 0,
    "wallet_balance": 0,
    "referrer_openid": "oc0ZD3eVZQs6UvBMNo91ZVlsCKdY",
    "my_invite_code": "",
    "created_at": "2026-03-30T12:47:30.000Z",
    "updated_at": "2026-03-30T13:07:38.000Z"
  },
  {
    "_id": "oc0ZD3VSTH7NkeQNx0sCzj-y8xFw",
    "_legacy_id": 117,
    "openid": "oc0ZD3VSTH7NkeQNx0sCzj-y8xFw",
    "nickName": "🌟卿贝贝🌟",
    "avatarUrl": "https://oss-1357612648.cos.ap-shanghai.myqcloud.com/users/avatars/1774945545243_6b461fb2c4845f71.jpeg",
    "phone": "",
    "role_level": 0,
    "distributor_level": 1,
    "points": 0,
    "wallet_balance": 0,
    "referrer_openid": "oc0ZD3YpHJvUxAK79fMjRKVlrvhk",
    "my_invite_code": "",
    "created_at": "2026-03-30T13:15:53.000Z",
    "updated_at": "2026-03-31T08:25:49.000Z"
  },
  {
    "_id": "oc0ZD3UloKBwkPsr23I2u3aZv9bs",
    "_legacy_id": 118,
    "openid": "oc0ZD3UloKBwkPsr23I2u3aZv9bs",
    "nickName": "微信用户",
    "avatarUrl": "/assets/images/default-avatar.svg",
    "phone": "",
    "role_level": 0,
    "distributor_level": 1,
    "points": 0,
    "wallet_balance": 0,
    "referrer_openid": "oc0ZD3XNpvPj9tJp3mwYdjWWDi3I",
    "my_invite_code": "",
    "created_at": "2026-03-30T15:46:44.000Z",
    "updated_at": "2026-03-30T15:46:44.000Z"
  },
  {
    "_id": "oc0ZD3SjFesod6fr3vdZGEh41Bek",
    "_legacy_id": 119,
    "openid": "oc0ZD3SjFesod6fr3vdZGEh41Bek",
    "nickName": "微信用户",
    "avatarUrl": "/assets/images/default-avatar.svg",
    "phone": "",
    "role_level": 0,
    "distributor_level": 1,
    "points": 0,
    "wallet_balance": 0,
    "referrer_openid": "",
    "my_invite_code": "",
    "created_at": "2026-03-30T15:58:20.000Z",
    "updated_at": "2026-04-01T04:49:03.000Z"
  },
  {
    "_id": "oc0ZD3W_dZBjaW_7oaeYK9iaQvH0",
    "_legacy_id": 120,
    "openid": "oc0ZD3W_dZBjaW_7oaeYK9iaQvH0",
    "nickName": "wxid_zhuebh9xv1gc12",
    "avatarUrl": "https://oss-1357612648.cos.ap-shanghai.myqcloud.com/users/avatars/1774886530973_22acf29f3b50f2ea.png",
    "phone": "",
    "role_level": 0,
    "distributor_level": 1,
    "points": 0,
    "wallet_balance": 0,
    "referrer_openid": "",
    "my_invite_code": "",
    "created_at": "2026-03-30T15:58:49.000Z",
    "updated_at": "2026-03-30T16:02:11.000Z"
  },
  {
    "_id": "oc0ZD3WdCIBaDudiPMW2IZaHM9uE",
    "_legacy_id": 121,
    "openid": "oc0ZD3WdCIBaDudiPMW2IZaHM9uE",
    "nickName": "春草",
    "avatarUrl": "https://oss-1357612648.cos.ap-shanghai.myqcloud.com/users/avatars/1774889044295_9769a718ff568b99.jpeg",
    "phone": "",
    "role_level": 0,
    "distributor_level": 1,
    "points": 0,
    "wallet_balance": 0,
    "referrer_openid": "oc0ZD3fqS26hEFVgq0z_RzMBqCTI",
    "my_invite_code": "",
    "created_at": "2026-03-30T16:14:50.000Z",
    "updated_at": "2026-04-06T10:29:51.000Z"
  },
  {
    "_id": "oc0ZD3dSDlItV2tOYHgYTubZAgVw",
    "_legacy_id": 122,
    "openid": "oc0ZD3dSDlItV2tOYHgYTubZAgVw",
    "nickName": "微信用户",
    "avatarUrl": "/assets/images/default-avatar.svg",
    "phone": "",
    "role_level": 0,
    "distributor_level": 1,
    "points": 0,
    "wallet_balance": 0,
    "referrer_openid": "oc0ZD3YeYm-5rTK8k8ew-1sBubJ8",
    "my_invite_code": "",
    "created_at": "2026-03-31T01:04:29.000Z",
    "updated_at": "2026-03-31T01:04:30.000Z"
  },
  {
    "_id": "oc0ZD3RsiSF6P448Q1XAs0MCkPqg",
    "_legacy_id": 123,
    "openid": "oc0ZD3RsiSF6P448Q1XAs0MCkPqg",
    "nickName": "微信用户",
    "avatarUrl": "/assets/images/default-avatar.svg",
    "phone": "",
    "role_level": 0,
    "distributor_level": 1,
    "points": 0,
    "wallet_balance": 0,
    "referrer_openid": "oc0ZD3evYUMnAPlVg6S_dbYngzn8",
    "my_invite_code": "",
    "created_at": "2026-03-31T01:50:46.000Z",
    "updated_at": "2026-03-31T01:50:46.000Z"
  },
  {
    "_id": "oc0ZD3a3iUukiAKHoS5gAXYLmfg8",
    "_legacy_id": 124,
    "openid": "oc0ZD3a3iUukiAKHoS5gAXYLmfg8",
    "nickName": "微信用户",
    "avatarUrl": "/assets/images/default-avatar.svg",
    "phone": "",
    "role_level": 0,
    "distributor_level": 1,
    "points": 0,
    "wallet_balance": 0,
    "referrer_openid": "oc0ZD3bYO0XafikXZptA_jhthCss",
    "my_invite_code": "",
    "created_at": "2026-03-31T02:24:45.000Z",
    "updated_at": "2026-03-31T02:24:45.000Z"
  },
  {
    "_id": "oc0ZD3dRZ7CkQNRAZ81L-Wy-jSzY",
    "_legacy_id": 125,
    "openid": "oc0ZD3dRZ7CkQNRAZ81L-Wy-jSzY",
    "nickName": "微信用户",
    "avatarUrl": "/assets/images/default-avatar.svg",
    "phone": "",
    "role_level": 0,
    "distributor_level": 1,
    "points": 0,
    "wallet_balance": 0,
    "referrer_openid": "",
    "my_invite_code": "",
    "created_at": "2026-03-31T03:06:58.000Z",
    "updated_at": "2026-03-31T03:06:58.000Z"
  },
  {
    "_id": "oc0ZD3bpR8sJO66108NTF2tK54j0",
    "_legacy_id": 126,
    "openid": "oc0ZD3bpR8sJO66108NTF2tK54j0",
    "nickName": "微信用户",
    "avatarUrl": "/assets/images/default-avatar.svg",
    "phone": "",
    "role_level": 0,
    "distributor_level": 1,
    "points": 0,
    "wallet_balance": 0,
    "referrer_openid": "oc0ZD3bYO0XafikXZptA_jhthCss",
    "my_invite_code": "",
    "created_at": "2026-03-31T03:54:44.000Z",
    "updated_at": "2026-03-31T03:54:44.000Z"
  },
  {
    "_id": "oc0ZD3SD8JjQQkCgGkYF92o3lE2E",
    "_legacy_id": 127,
    "openid": "oc0ZD3SD8JjQQkCgGkYF92o3lE2E",
    "nickName": "微信用户",
    "avatarUrl": "/assets/images/default-avatar.svg",
    "phone": "",
    "role_level": 0,
    "distributor_level": 1,
    "points": 0,
    "wallet_balance": 0,
    "referrer_openid": "oc0ZD3bYO0XafikXZptA_jhthCss",
    "my_invite_code": "",
    "created_at": "2026-03-31T06:42:19.000Z",
    "updated_at": "2026-03-31T06:42:19.000Z"
  },
  {
    "_id": "oc0ZD3VrGzinF9-9x2t1fnrPxgbQ",
    "_legacy_id": 128,
    "openid": "oc0ZD3VrGzinF9-9x2t1fnrPxgbQ",
    "nickName": "微信用户",
    "avatarUrl": "/assets/images/default-avatar.svg",
    "phone": "",
    "role_level": 0,
    "distributor_level": 1,
    "points": 0,
    "wallet_balance": 0,
    "referrer_openid": "",
    "my_invite_code": "",
    "created_at": "2026-03-31T07:55:32.000Z",
    "updated_at": "2026-03-31T07:55:32.000Z"
  },
  {
    "_id": "oc0ZD3Vb_B1Q2pGp7qRy4SdsNYWw",
    "_legacy_id": 129,
    "openid": "oc0ZD3Vb_B1Q2pGp7qRy4SdsNYWw",
    "nickName": "胡啦",
    "avatarUrl": "https://oss-1357612648.cos.ap-shanghai.myqcloud.com/users/avatars/1774963430506_93d2fde9994fb7cf.jpeg",
    "phone": "",
    "role_level": 0,
    "distributor_level": 1,
    "points": 0,
    "wallet_balance": 0,
    "referrer_openid": "oc0ZD3XxzPISJj9epmRvGrOApzQ4",
    "my_invite_code": "",
    "created_at": "2026-03-31T13:23:43.000Z",
    "updated_at": "2026-03-31T13:23:54.000Z"
  },
  {
    "_id": "oc0ZD3T6uQ1b4SF5FVk9226I1Vng",
    "_legacy_id": 130,
    "openid": "oc0ZD3T6uQ1b4SF5FVk9226I1Vng",
    "nickName": "微信用户",
    "avatarUrl": "/assets/images/default-avatar.svg",
    "phone": "",
    "role_level": 0,
    "distributor_level": 1,
    "points": 0,
    "wallet_balance": 0,
    "referrer_openid": "",
    "my_invite_code": "",
    "created_at": "2026-03-31T15:34:11.000Z",
    "updated_at": "2026-03-31T15:34:11.000Z"
  },
  {
    "_id": "oc0ZD3QQH3HMFsaGczqAXi794S8c",
    "_legacy_id": 131,
    "openid": "oc0ZD3QQH3HMFsaGczqAXi794S8c",
    "nickName": "微信用户",
    "avatarUrl": "/assets/images/default-avatar.svg",
    "phone": "",
    "role_level": 0,
    "distributor_level": 1,
    "points": 0,
    "wallet_balance": 0,
    "referrer_openid": "",
    "my_invite_code": "",
    "created_at": "2026-04-01T01:14:05.000Z",
    "updated_at": "2026-04-01T01:14:05.000Z"
  },
  {
    "_id": "oc0ZD3d-E8wk5jFHFbq8oq2qOgFE",
    "_legacy_id": 132,
    "openid": "oc0ZD3d-E8wk5jFHFbq8oq2qOgFE",
    "nickName": "微信用户",
    "avatarUrl": "/assets/images/default-avatar.svg",
    "phone": "",
    "role_level": 0,
    "distributor_level": 1,
    "points": 0,
    "wallet_balance": 0,
    "referrer_openid": "",
    "my_invite_code": "",
    "created_at": "2026-04-01T01:56:38.000Z",
    "updated_at": "2026-04-01T01:56:38.000Z"
  },
  {
    "_id": "oc0ZD3eVoNOOHN-5mIc0Wixc9iVY",
    "_legacy_id": 133,
    "openid": "oc0ZD3eVoNOOHN-5mIc0Wixc9iVY",
    "nickName": "微信用户",
    "avatarUrl": "/assets/images/default-avatar.svg",
    "phone": "",
    "role_level": 0,
    "distributor_level": 1,
    "points": 0,
    "wallet_balance": 0,
    "referrer_openid": "oc0ZD3XxzPISJj9epmRvGrOApzQ4",
    "my_invite_code": "",
    "created_at": "2026-04-01T02:09:34.000Z",
    "updated_at": "2026-04-01T02:09:34.000Z"
  },
  {
    "_id": "oc0ZD3ehXwz9STipL3TgdqvUThSg",
    "_legacy_id": 134,
    "openid": "oc0ZD3ehXwz9STipL3TgdqvUThSg",
    "nickName": "舍",
    "avatarUrl": "https://oss-1357612648.cos.ap-shanghai.myqcloud.com/users/avatars/1775017701792_eb46fc0ba680f8c6.jpeg",
    "phone": "",
    "role_level": 0,
    "distributor_level": 1,
    "points": 0,
    "wallet_balance": 0,
    "referrer_openid": "oc0ZD3fqS26hEFVgq0z_RzMBqCTI",
    "my_invite_code": "",
    "created_at": "2026-04-01T04:28:02.000Z",
    "updated_at": "2026-04-01T04:28:25.000Z"
  },
  {
    "_id": "oc0ZD3f0vK4Qwhnnq2Bt1o6p-sSc",
    "_legacy_id": 135,
    "openid": "oc0ZD3f0vK4Qwhnnq2Bt1o6p-sSc",
    "nickName": "wxid_k3i5hyz8czt712",
    "avatarUrl": "https://oss-1357612648.cos.ap-shanghai.myqcloud.com/users/avatars/1775019185284_f5b1b261e92c6ded.png",
    "phone": "",
    "role_level": 0,
    "distributor_level": 1,
    "points": 0,
    "wallet_balance": 0,
    "referrer_openid": "",
    "my_invite_code": "",
    "created_at": "2026-04-01T04:49:12.000Z",
    "updated_at": "2026-04-01T04:54:53.000Z"
  },
  {
    "_id": "oc0ZD3WXYNeWJNGDhlXofsSwNDeE",
    "_legacy_id": 136,
    "openid": "oc0ZD3WXYNeWJNGDhlXofsSwNDeE",
    "nickName": "微信用户",
    "avatarUrl": "/assets/images/default-avatar.svg",
    "phone": "",
    "role_level": 0,
    "distributor_level": 1,
    "points": 0,
    "wallet_balance": 0,
    "referrer_openid": "oc0ZD3VcqiZEYUq0fuoxs0_voozI",
    "my_invite_code": "",
    "created_at": "2026-04-01T06:03:05.000Z",
    "updated_at": "2026-04-01T06:03:05.000Z"
  },
  {
    "_id": "oc0ZD3fma4quTK9b9YH4Me022E0U",
    "_legacy_id": 137,
    "openid": "oc0ZD3fma4quTK9b9YH4Me022E0U",
    "nickName": "微信用户",
    "avatarUrl": "/assets/images/default-avatar.svg",
    "phone": "",
    "role_level": 0,
    "distributor_level": 1,
    "points": 0,
    "wallet_balance": 0,
    "referrer_openid": "oc0ZD3fqS26hEFVgq0z_RzMBqCTI",
    "my_invite_code": "",
    "created_at": "2026-04-01T06:46:26.000Z",
    "updated_at": "2026-04-01T06:46:26.000Z"
  },
  {
    "_id": "oc0ZD3Tt3cNNBYGamhiqWBuaP5EU",
    "_legacy_id": 138,
    "openid": "oc0ZD3Tt3cNNBYGamhiqWBuaP5EU",
    "nickName": "微信用户",
    "avatarUrl": "/assets/images/default-avatar.svg",
    "phone": "",
    "role_level": 0,
    "distributor_level": 1,
    "points": 0,
    "wallet_balance": 0,
    "referrer_openid": "oc0ZD3XSX5ZoTpG21QUrcWVipLj8",
    "my_invite_code": "",
    "created_at": "2026-04-01T09:16:21.000Z",
    "updated_at": "2026-04-01T09:16:21.000Z"
  },
  {
    "_id": "oc0ZD3WfEB070s-HjQi-2JhjNlAQ",
    "_legacy_id": 139,
    "openid": "oc0ZD3WfEB070s-HjQi-2JhjNlAQ",
    "nickName": "微信用户",
    "avatarUrl": "/assets/images/default-avatar.svg",
    "phone": "",
    "role_level": 0,
    "distributor_level": 1,
    "points": 0,
    "wallet_balance": 0,
    "referrer_openid": "oc0ZD3VTKxBlvH1PIilOFSD1VU7c",
    "my_invite_code": "",
    "created_at": "2026-04-01T09:20:38.000Z",
    "updated_at": "2026-04-01T09:20:38.000Z"
  },
  {
    "_id": "oc0ZD3VbpKMx0qbgSAQykd-YSzus",
    "_legacy_id": 140,
    "openid": "oc0ZD3VbpKMx0qbgSAQykd-YSzus",
    "nickName": "微信用户",
    "avatarUrl": "/assets/images/default-avatar.svg",
    "phone": "",
    "role_level": 0,
    "distributor_level": 1,
    "points": 0,
    "wallet_balance": 0,
    "referrer_openid": "oc0ZD3VcqiZEYUq0fuoxs0_voozI",
    "my_invite_code": "",
    "created_at": "2026-04-01T10:25:58.000Z",
    "updated_at": "2026-04-01T10:25:58.000Z"
  },
  {
    "_id": "oc0ZD3XkLx6XWxMKN8tAXPNfSqlI",
    "_legacy_id": 141,
    "openid": "oc0ZD3XkLx6XWxMKN8tAXPNfSqlI",
    "nickName": "🧊",
    "avatarUrl": "https://oss-1357612648.cos.ap-shanghai.myqcloud.com/users/avatars/1775039715382_c23a90521e24edbc.jpg",
    "phone": "",
    "role_level": 0,
    "distributor_level": 1,
    "points": 0,
    "wallet_balance": 0,
    "referrer_openid": "oc0ZD3evYUMnAPlVg6S_dbYngzn8",
    "my_invite_code": "",
    "created_at": "2026-04-01T10:34:18.000Z",
    "updated_at": "2026-04-01T10:35:15.000Z"
  },
  {
    "_id": "oc0ZD3fHyWyxkmwsTVlDw-pUGMaw",
    "_legacy_id": 142,
    "openid": "oc0ZD3fHyWyxkmwsTVlDw-pUGMaw",
    "nickName": "糕糕高教数学",
    "avatarUrl": "https://oss-1357612648.cos.ap-shanghai.myqcloud.com/users/avatars/1775051281861_32842bd33f2cff17.jpeg",
    "phone": "",
    "role_level": 0,
    "distributor_level": 1,
    "points": 0,
    "wallet_balance": 0,
    "referrer_openid": "oc0ZD3SvIQErMkhXqJxz1Kk5k2Dc",
    "my_invite_code": "",
    "created_at": "2026-04-01T13:47:51.000Z",
    "updated_at": "2026-04-01T13:48:08.000Z"
  },
  {
    "_id": "oc0ZD3ZCoOKBmJK2OBUJ-HbI_j2Y",
    "_legacy_id": 143,
    "openid": "oc0ZD3ZCoOKBmJK2OBUJ-HbI_j2Y",
    "nickName": "小杜",
    "avatarUrl": "https://oss-1357612648.cos.ap-shanghai.myqcloud.com/users/avatars/1775051796525_c6d9898e5f5ddfa0.jpeg",
    "phone": "",
    "role_level": 0,
    "distributor_level": 1,
    "points": 0,
    "wallet_balance": 0,
    "referrer_openid": "",
    "my_invite_code": "",
    "created_at": "2026-04-01T13:53:25.000Z",
    "updated_at": "2026-04-06T14:16:18.000Z"
  },
  {
    "_id": "oc0ZD3dBANP1Xxo_rO9pxJ60x5LE",
    "_legacy_id": 144,
    "openid": "oc0ZD3dBANP1Xxo_rO9pxJ60x5LE",
    "nickName": "微信用户",
    "avatarUrl": "/assets/images/default-avatar.svg",
    "phone": "",
    "role_level": 0,
    "distributor_level": 1,
    "points": 0,
    "wallet_balance": 0,
    "referrer_openid": "oc0ZD3Yw5MwjDzFi_yF7B7a8Z2mw",
    "my_invite_code": "",
    "created_at": "2026-04-02T06:10:00.000Z",
    "updated_at": "2026-04-02T06:10:00.000Z"
  },
  {
    "_id": "oc0ZD3difKb1lMCRyIdXtyB4qR80",
    "_legacy_id": 145,
    "openid": "oc0ZD3difKb1lMCRyIdXtyB4qR80",
    "nickName": "小张",
    "avatarUrl": "https://oss-1357612648.cos.ap-shanghai.myqcloud.com/users/avatars/1775123694929_e61ac7367adee8a9.jpeg",
    "phone": "",
    "role_level": 1,
    "distributor_level": 1,
    "points": 399,
    "wallet_balance": 0,
    "referrer_openid": "oc0ZD3XxzPISJj9epmRvGrOApzQ4",
    "my_invite_code": "",
    "created_at": "2026-04-02T09:54:29.000Z",
    "updated_at": "2026-04-02T09:57:59.000Z"
  },
  {
    "_id": "oc0ZD3Tx5dZdM18G7zOh9LaMC61U",
    "_legacy_id": 146,
    "openid": "oc0ZD3Tx5dZdM18G7zOh9LaMC61U",
    "nickName": "微信用户",
    "avatarUrl": "/assets/images/default-avatar.svg",
    "phone": "",
    "role_level": 0,
    "distributor_level": 1,
    "points": 0,
    "wallet_balance": 0,
    "referrer_openid": "oc0ZD3XSX5ZoTpG21QUrcWVipLj8",
    "my_invite_code": "",
    "created_at": "2026-04-03T03:41:06.000Z",
    "updated_at": "2026-04-03T03:41:06.000Z"
  },
  {
    "_id": "oc0ZD3TY_X6d4Ch68oADcgqkVrbc",
    "_legacy_id": 147,
    "openid": "oc0ZD3TY_X6d4Ch68oADcgqkVrbc",
    "nickName": "微信用户",
    "avatarUrl": "/assets/images/default-avatar.svg",
    "phone": "",
    "role_level": 0,
    "distributor_level": 1,
    "points": 0,
    "wallet_balance": 0,
    "referrer_openid": "oc0ZD3XSX5ZoTpG21QUrcWVipLj8",
    "my_invite_code": "",
    "created_at": "2026-04-03T08:03:34.000Z",
    "updated_at": "2026-04-03T08:03:34.000Z"
  },
  {
    "_id": "oc0ZD3SiJ3g8Mg7qu_r86G0XFf2s",
    "_legacy_id": 148,
    "openid": "oc0ZD3SiJ3g8Mg7qu_r86G0XFf2s",
    "nickName": "不沉沦的小檬",
    "avatarUrl": "https://oss-1357612648.cos.ap-shanghai.myqcloud.com/users/avatars/1775233471311_aefbad7e2114c8fa.jpeg",
    "phone": "",
    "role_level": 0,
    "distributor_level": 1,
    "points": 0,
    "wallet_balance": 0,
    "referrer_openid": "oc0ZD3Yw5MwjDzFi_yF7B7a8Z2mw",
    "my_invite_code": "",
    "created_at": "2026-04-03T16:24:12.000Z",
    "updated_at": "2026-04-03T16:24:42.000Z"
  },
  {
    "_id": "oc0ZD3afDwz51fzOR8kq3NpMBofY",
    "_legacy_id": 149,
    "openid": "oc0ZD3afDwz51fzOR8kq3NpMBofY",
    "nickName": "微信用户",
    "avatarUrl": "/assets/images/default-avatar.svg",
    "phone": "",
    "role_level": 0,
    "distributor_level": 1,
    "points": 0,
    "wallet_balance": 0,
    "referrer_openid": "oc0ZD3Y5yrF5ezpwwSPUtkJWna1Q",
    "my_invite_code": "",
    "created_at": "2026-04-05T13:27:34.000Z",
    "updated_at": "2026-04-07T07:53:50.000Z"
  },
  {
    "_id": "oc0ZD3Y_LN2tyER5T4snWsUfybSg",
    "_legacy_id": 150,
    "openid": "oc0ZD3Y_LN2tyER5T4snWsUfybSg",
    "nickName": "微信用户",
    "avatarUrl": "https://oss-1357612648.cos.ap-shanghai.myqcloud.com/users/avatars/1775404542882_2b49fe88a0da3de7.jpeg",
    "phone": "",
    "role_level": 0,
    "distributor_level": 1,
    "points": 0,
    "wallet_balance": 0,
    "referrer_openid": "",
    "my_invite_code": "",
    "created_at": "2026-04-05T15:45:59.000Z",
    "updated_at": "2026-04-05T15:55:43.000Z"
  },
  {
    "_id": "oc0ZD3bhXwW8yrqHPKv6wn7PhYvg",
    "_legacy_id": 151,
    "openid": "oc0ZD3bhXwW8yrqHPKv6wn7PhYvg",
    "nickName": "徊枝",
    "avatarUrl": "https://oss-1357612648.cos.ap-shanghai.myqcloud.com/users/avatars/1775405485611_032be4f9cd147c26.jpeg",
    "phone": "",
    "role_level": 0,
    "distributor_level": 1,
    "points": 0,
    "wallet_balance": 0,
    "referrer_openid": "",
    "my_invite_code": "",
    "created_at": "2026-04-05T16:10:38.000Z",
    "updated_at": "2026-04-05T16:11:32.000Z"
  },
  {
    "_id": "oc0ZD3Sf8-rb4hxUVf3UUYOkUiO4",
    "_legacy_id": 152,
    "openid": "oc0ZD3Sf8-rb4hxUVf3UUYOkUiO4",
    "nickName": "微信用户",
    "avatarUrl": "",
    "phone": "",
    "role_level": 0,
    "distributor_level": 1,
    "points": 0,
    "wallet_balance": 0,
    "referrer_openid": "",
    "my_invite_code": "",
    "created_at": "2026-04-06T04:07:29.000Z",
    "updated_at": "2026-04-06T04:07:29.000Z"
  },
  {
    "_id": "oc0ZD3ZJBO7cZ-D4zn7VFgr-Am4M",
    "_legacy_id": 153,
    "openid": "oc0ZD3ZJBO7cZ-D4zn7VFgr-Am4M",
    "nickName": "微信用户",
    "avatarUrl": "/assets/images/default-avatar.svg",
    "phone": "",
    "role_level": 0,
    "distributor_level": 1,
    "points": 0,
    "wallet_balance": 0,
    "referrer_openid": "oc0ZD3WdCIBaDudiPMW2IZaHM9uE",
    "my_invite_code": "",
    "created_at": "2026-04-06T09:00:40.000Z",
    "updated_at": "2026-04-06T10:30:32.000Z"
  },
  {
    "_id": "oc0ZD3a1pPvq4YLRqTrhj_xsHRy8",
    "_legacy_id": 154,
    "openid": "oc0ZD3a1pPvq4YLRqTrhj_xsHRy8",
    "nickName": "微信用户",
    "avatarUrl": "/assets/images/default-avatar.svg",
    "phone": "",
    "role_level": 0,
    "distributor_level": 1,
    "points": 0,
    "wallet_balance": 0,
    "referrer_openid": "",
    "my_invite_code": "",
    "created_at": "2026-04-06T11:02:49.000Z",
    "updated_at": "2026-04-06T11:02:49.000Z"
  },
  {
    "_id": "oc0ZD3c4z2sPfe3Zx__MOq_c2Mds",
    "_legacy_id": 155,
    "openid": "oc0ZD3c4z2sPfe3Zx__MOq_c2Mds",
    "nickName": "微信用户",
    "avatarUrl": "/assets/images/default-avatar.svg",
    "phone": "",
    "role_level": 0,
    "distributor_level": 1,
    "points": 0,
    "wallet_balance": 0,
    "referrer_openid": "",
    "my_invite_code": "",
    "created_at": "2026-04-06T11:05:00.000Z",
    "updated_at": "2026-04-06T11:05:00.000Z"
  },
  {
    "_id": "oc0ZD3R_hz4Q_-prCjI4Di_s7SAA",
    "_legacy_id": 156,
    "openid": "oc0ZD3R_hz4Q_-prCjI4Di_s7SAA",
    "nickName": "微信用户",
    "avatarUrl": "/assets/images/default-avatar.svg",
    "phone": "",
    "role_level": 0,
    "distributor_level": 1,
    "points": 0,
    "wallet_balance": 0,
    "referrer_openid": "",
    "my_invite_code": "",
    "created_at": "2026-04-06T11:06:43.000Z",
    "updated_at": "2026-04-06T11:06:43.000Z"
  },
  {
    "_id": "oc0ZD3YqqgLDKBmcyRb4d2739Ugc",
    "_legacy_id": 157,
    "openid": "oc0ZD3YqqgLDKBmcyRb4d2739Ugc",
    "nickName": "微信用户",
    "avatarUrl": "/assets/images/default-avatar.svg",
    "phone": "",
    "role_level": 0,
    "distributor_level": 1,
    "points": 0,
    "wallet_balance": 0,
    "referrer_openid": "",
    "my_invite_code": "",
    "created_at": "2026-04-06T11:12:33.000Z",
    "updated_at": "2026-04-06T11:12:33.000Z"
  },
  {
    "_id": "oc0ZD3ZPJLe0r_qyJF40ndmf6ZNo",
    "_legacy_id": 158,
    "openid": "oc0ZD3ZPJLe0r_qyJF40ndmf6ZNo",
    "nickName": "微信用户",
    "avatarUrl": "/assets/images/default-avatar.svg",
    "phone": "",
    "role_level": 0,
    "distributor_level": 1,
    "points": 0,
    "wallet_balance": 0,
    "referrer_openid": "",
    "my_invite_code": "",
    "created_at": "2026-04-06T11:19:24.000Z",
    "updated_at": "2026-04-06T11:19:24.000Z"
  },
  {
    "_id": "oc0ZD3cnyhVaYM9-da7Yok9f0dro",
    "_legacy_id": 159,
    "openid": "oc0ZD3cnyhVaYM9-da7Yok9f0dro",
    "nickName": "微信用户",
    "avatarUrl": "/assets/images/default-avatar.svg",
    "phone": "",
    "role_level": 0,
    "distributor_level": 1,
    "points": 0,
    "wallet_balance": 0,
    "referrer_openid": "",
    "my_invite_code": "",
    "created_at": "2026-04-06T11:39:50.000Z",
    "updated_at": "2026-04-06T11:39:50.000Z"
  },
  {
    "_id": "oc0ZD3WPcSGjAUkplqHzotvRG-48",
    "_legacy_id": 160,
    "openid": "oc0ZD3WPcSGjAUkplqHzotvRG-48",
    "nickName": "微信用户",
    "avatarUrl": "/assets/images/default-avatar.svg",
    "phone": "",
    "role_level": 0,
    "distributor_level": 1,
    "points": 0,
    "wallet_balance": 0,
    "referrer_openid": "",
    "my_invite_code": "",
    "created_at": "2026-04-06T11:45:27.000Z",
    "updated_at": "2026-04-06T11:45:27.000Z"
  },
  {
    "_id": "oc0ZD3V648ng8J1nq-MOdcZxtg9I",
    "_legacy_id": 161,
    "openid": "oc0ZD3V648ng8J1nq-MOdcZxtg9I",
    "nickName": "微信用户",
    "avatarUrl": "/assets/images/default-avatar.svg",
    "phone": "",
    "role_level": 0,
    "distributor_level": 1,
    "points": 0,
    "wallet_balance": 0,
    "referrer_openid": "",
    "my_invite_code": "",
    "created_at": "2026-04-06T13:28:51.000Z",
    "updated_at": "2026-04-06T13:28:51.000Z"
  },
  {
    "_id": "oc0ZD3XEFKAPHN4tEXMhqkBfeHyQ",
    "_legacy_id": 162,
    "openid": "oc0ZD3XEFKAPHN4tEXMhqkBfeHyQ",
    "nickName": "微信用户",
    "avatarUrl": "/assets/images/default-avatar.svg",
    "phone": "",
    "role_level": 0,
    "distributor_level": 1,
    "points": 0,
    "wallet_balance": 0,
    "referrer_openid": "",
    "my_invite_code": "",
    "created_at": "2026-04-06T13:34:07.000Z",
    "updated_at": "2026-04-06T13:34:07.000Z"
  },
  {
    "_id": "oc0ZD3YVsndRC_RxTCNUoNZoctBI",
    "_legacy_id": 163,
    "openid": "oc0ZD3YVsndRC_RxTCNUoNZoctBI",
    "nickName": "微信用户",
    "avatarUrl": "/assets/images/default-avatar.svg",
    "phone": "",
    "role_level": 0,
    "distributor_level": 1,
    "points": 0,
    "wallet_balance": 0,
    "referrer_openid": "oc0ZD3ZCoOKBmJK2OBUJ-HbI_j2Y",
    "my_invite_code": "",
    "created_at": "2026-04-06T14:14:18.000Z",
    "updated_at": "2026-04-06T14:14:18.000Z"
  },
  {
    "_id": "oc0ZD3TjEnKYuHz1nrPWIFGQT6Zg",
    "_legacy_id": 164,
    "openid": "oc0ZD3TjEnKYuHz1nrPWIFGQT6Zg",
    "nickName": "微信用户",
    "avatarUrl": "/assets/images/default-avatar.svg",
    "phone": "",
    "role_level": 0,
    "distributor_level": 1,
    "points": 0,
    "wallet_balance": 0,
    "referrer_openid": "oc0ZD3ZCoOKBmJK2OBUJ-HbI_j2Y",
    "my_invite_code": "",
    "created_at": "2026-04-06T14:15:35.000Z",
    "updated_at": "2026-04-06T14:15:35.000Z"
  },
  {
    "_id": "oc0ZD3eXy_BVDs1h0x06nkoLeO48",
    "_legacy_id": 165,
    "openid": "oc0ZD3eXy_BVDs1h0x06nkoLeO48",
    "nickName": "微信用户",
    "avatarUrl": "/assets/images/default-avatar.svg",
    "phone": "",
    "role_level": 0,
    "distributor_level": 1,
    "points": 0,
    "wallet_balance": 0,
    "referrer_openid": "oc0ZD3ZCoOKBmJK2OBUJ-HbI_j2Y",
    "my_invite_code": "",
    "created_at": "2026-04-06T14:16:18.000Z",
    "updated_at": "2026-04-06T14:16:18.000Z"
  },
  {
    "_id": "oc0ZD3fyusP8wUIoiaE6iaQ4PT9o",
    "_legacy_id": 166,
    "openid": "oc0ZD3fyusP8wUIoiaE6iaQ4PT9o",
    "nickName": "wxid_5psgzmjoviih12",
    "avatarUrl": "https://oss-1357612648.cos.ap-shanghai.myqcloud.com/users/avatars/1775490671420_656fcd75bb99b4f4.png",
    "phone": "",
    "role_level": 0,
    "distributor_level": 1,
    "points": 0,
    "wallet_balance": 0,
    "referrer_openid": "",
    "my_invite_code": "",
    "created_at": "2026-04-06T15:46:52.000Z",
    "updated_at": "2026-04-06T15:51:11.000Z"
  },
  {
    "_id": "oc0ZD3cdCdZS2e3TVUvvR9f0cFAw",
    "_legacy_id": 167,
    "openid": "oc0ZD3cdCdZS2e3TVUvvR9f0cFAw",
    "nickName": "微信用户",
    "avatarUrl": "https://oss-1357612648.cos.ap-shanghai.myqcloud.com/users/avatars/1775491767319_43dded02cca7a124.jpeg",
    "phone": "",
    "role_level": 0,
    "distributor_level": 1,
    "points": 0,
    "wallet_balance": 0,
    "referrer_openid": "oc0ZD3Yw5MwjDzFi_yF7B7a8Z2mw",
    "my_invite_code": "",
    "created_at": "2026-04-06T16:09:18.000Z",
    "updated_at": "2026-04-06T16:09:27.000Z"
  },
  {
    "_id": "oc0ZD3bpq0syzuXnKHDA7Ha-AxXY",
    "_legacy_id": 168,
    "openid": "oc0ZD3bpq0syzuXnKHDA7Ha-AxXY",
    "nickName": "微信用户",
    "avatarUrl": "/assets/images/default-avatar.svg",
    "phone": "",
    "role_level": 0,
    "distributor_level": 1,
    "points": 0,
    "wallet_balance": 0,
    "referrer_openid": "",
    "my_invite_code": "",
    "created_at": "2026-04-07T02:49:18.000Z",
    "updated_at": "2026-04-07T02:49:18.000Z"
  }
]