{
  "generatedAt": "2026-04-25T03:33:20.174Z",
  "ok": true,
  "steps": [
    {
      "name": "financeFirewall",
      "ok": true,
      "brief": "缺口项 0",
      "output": "\n> cloud-mp-foundation@0.1.0 audit:finance-firewall\n> node scripts/audit-strategic-finance-firewall.js\n\n{\n  \"generated_at\": \"2026-04-25T03:33:31.595Z\",\n  \"summary\": {\n    \"missing_internal_wallet_logs\": 0,\n    \"missing_internal_goods_fund_logs\": 0,\n    \"ignored_goods_fund_test_refunds\": 9,\n    \"missing_reopen_reversal_logs\": 0,\n    \"missing_adjustment_reasons\": 0,\n    \"missing_debt_reasons\": 0,\n    \"missing_dividend_remarks\": 0,\n    \"missing_exit_review_remarks\": 0\n  },\n  \"findings\": {\n    \"missingInternalWalletLogs\": [],\n    \"missingInternalGoodsFundLogs\": [],\n    \"ignoredGoodsFundTestRefunds\": [\n      \"REF1775993281617789 / ORD1775992929604326\",\n      \"REF1776058290289539 / ORD1776006098733948\",\n      \"REF1776083909694275 / ORD1776077635910944\",\n      \"REF1776089368463924 / ORD1776088274225191\",\n      \"REF1776180590451998 / ORD1776180331262593\",\n      \"REF1776328201267101 / ORD1776172821100816\",\n      \"REF1776328202523576 / ORD177617628123673\",\n      \"REF1776328204080828 / ORD1776239193669385\",\n      \"REF1777047004943126 / ORD177608386229345\"\n    ],\n    \"missingReopenReversalLogs\": [],\n    \"missingAdjustmentReasons\": [],\n    \"missingDebtReasons\": [],\n    \"missingDividendRemarks\": [],\n    \"missingExitReviewRemarks\": []\n  }\n}\n"
    },
    {
      "name": "refundRecon",
      "ok": true,
      "brief": "退款 34 笔，微信 15，原始未知 12，推断微信 5，测试忽略 19",
      "output": "\n> cloud-mp-foundation@0.1.0 audit:refunds\n> node scripts/audit-refund-reconciliation.js\n\n{\n  \"ok\": true,\n  \"json\": \"C:\\\\Users\\\\21963\\\\WeChatProjects\\\\zz\\\\cloud-mp\\\\docs\\\\audit\\\\generated\\\\REFUND_RECON_AUDIT.json\",\n  \"markdown\": \"C:\\\\Users\\\\21963\\\\WeChatProjects\\\\zz\\\\cloud-mp\\\\docs\\\\audit\\\\generated\\\\REFUND_RECON_AUDIT.md\",\n  \"summary\": {\n    \"total_refunds\": 34,\n    \"audited_refunds\": 34,\n    \"wechat_refunds\": 15,\n    \"internal_refunds\": 19,\n    \"actionable_refunds\": 3,\n    \"unknown_channel_refunds\": 12,\n    \"inferred_wechat_refunds\": 5,\n    \"ignored_test_refunds\": 19,\n    \"actions\": {\n      \"noop\": 12,\n      \"ignored_test_wallet\": 3,\n      \"ignored_test_unknown\": 7,\n      \"wechat_refund_not_found\": 2,\n      \"sync_to_completed\": 1,\n      \"ignored_test_goods_fund\": 9\n    },\n    \"severities\": {\n      \"ok\": 12,\n      \"info\": 19,\n      \"warning\": 2,\n      \"high\": 1\n    }\n  },\n  \"wechatQuery\": {\n    \"available\": true,\n    \"reason\": \"\",\n    \"attempted\": 15,\n    \"skipped\": 0,\n    \"query_limit\": 100\n  }\n}\n"
    },
    {
      "name": "financeSmoke",
      "ok": true,
      "brief": "接口 7 个，失败 0 个",
      "output": "{\n  \"ok\": true,\n  \"jsonPath\": \"C:\\\\Users\\\\21963\\\\WeChatProjects\\\\zz\\\\cloud-mp\\\\docs\\\\audit\\\\generated\\\\FINANCE_SMOKE_AUDIT.json\",\n  \"mdPath\": \"C:\\\\Users\\\\21963\\\\WeChatProjects\\\\zz\\\\cloud-mp\\\\docs\\\\audit\\\\generated\\\\FINANCE_SMOKE_AUDIT.md\",\n  \"results\": [\n    {\n      \"name\": \"refunds\",\n      \"collectionName\": \"refunds\",\n      \"ok\": true,\n      \"count\": 34,\n      \"issues\": []\n    },\n    {\n      \"name\": \"withdrawals\",\n      \"collectionName\": \"withdrawals\",\n      \"ok\": true,\n      \"count\": 6,\n      \"issues\": []\n    },\n    {\n      \"name\": \"commissions\",\n      \"collectionName\": \"commissions\",\n      \"ok\": true,\n      \"count\": 10,\n      \"issues\": []\n    },\n    {\n      \"name\": \"wallet_logs\",\n      \"collectionName\": \"wallet_logs\",\n      \"ok\": true,\n      \"count\": 49,\n      \"issues\": []\n    },\n    {\n      \"name\": \"goods_fund_logs\",\n      \"collectionName\": \"goods_fund_logs\",\n      \"ok\": true,\n      \"count\": 39,\n      \"issues\": []\n    },\n    {\n      \"name\": \"point_logs\",\n      \"collectionName\": \"point_logs\",\n      \"ok\": true,\n      \"count\": 696,\n      \"issues\": []\n    },\n    {\n      \"name\": \"users\",\n      \"collectionName\": \"users\",\n      \"ok\": true,\n      \"count\": 213,\n      \"issues\": []\n    }\n  ]\n}\n"
    },
    {
      "name": "financeSyntax",
      "ok": true,
      "brief": "文件 6 个，失败 0 个",
      "output": "{\n  \"ok\": true,\n  \"jsonPath\": \"C:\\\\Users\\\\21963\\\\WeChatProjects\\\\zz\\\\cloud-mp\\\\docs\\\\audit\\\\generated\\\\FINANCE_FUNCTION_SYNTAX_CHECK.json\",\n  \"mdPath\": \"C:\\\\Users\\\\21963\\\\WeChatProjects\\\\zz\\\\cloud-mp\\\\docs\\\\audit\\\\generated\\\\FINANCE_FUNCTION_SYNTAX_CHECK.md\",\n  \"results\": [\n    {\n      \"file\": \"cloudfunctions/admin-api/src/app.js\",\n      \"ok\": true,\n      \"output\": \"\"\n    },\n    {\n      \"file\": \"cloudfunctions/admin-api/src/admin-marketing.js\",\n      \"ok\": true,\n      \"output\": \"\"\n    },\n    {\n      \"file\": \"cloudfunctions/distribution/index.js\",\n      \"ok\": true,\n      \"output\": \"\"\n    },\n    {\n      \"file\": \"cloudfunctions/distribution/distribution-commission.js\",\n      \"ok\": true,\n      \"output\": \"\"\n    },\n    {\n      \"file\": \"cloudfunctions/payment/payment-prepay.js\",\n      \"ok\": true,\n      \"output\": \"\"\n    },\n    {\n      \"file\": \"cloudfunctions/order/order-create.js\",\n      \"ok\": true,\n      \"output\": \"\"\n    }\n  ]\n}\n"
    },
    {
      "name": "adminBuild",
      "ok": true,
      "brief": "admin-ui 构建通过",
      "output": "\n> admin-ui@1.0.0 build\n> vite build\n\n\u001b[36mvite v5.4.21 \u001b[32mbuilding for production...\u001b[36m\u001b[39m\ntransforming...\n\u001b[32m✓\u001b[39m 1789 modules transformed.\nrendering chunks...\ncomputing gzip size...\n\u001b[2mdist/\u001b[22m\u001b[32mindex.html                                 \u001b[39m\u001b[1m\u001b[2m  1.29 kB\u001b[22m\u001b[1m\u001b[22m\u001b[2m │ gzip:  0.73 kB\u001b[22m\n\u001b[2mdist/\u001b[22m\u001b[35massets/el-checkbox-group-D_6SYB2i.css      \u001b[39m\u001b[1m\u001b[2m  0.05 kB\u001b[22m\u001b[1m\u001b[22m\u001b[2m │ gzip:  0.07 kB\u001b[22m\n\u001b[2mdist/\u001b[22m\u001b[35massets/index-CAhJ0zP6.css                  \u001b[39m\u001b[1m\u001b[2m  0.05 kB\u001b[22m\u001b[1m\u001b[22m\u001b[2m │ gzip:  0.07 kB\u001b[22m\n\u001b[2mdist/\u001b[22m\u001b[35massets/el-radio-group-BzMpJalG.css         \u001b[39m\u001b[1m\u001b[2m  0.08 kB\u001b[22m\u001b[1m\u001b[22m\u001b[2m │ gzip:  0.09 kB\u001b[22m\n\u001b[2mdist/\u001b[22m\u001b[35massets/index-Cj1qSbQg.css                  \u001b[39m\u001b[1m\u001b[2m  0.09 kB\u001b[22m\u001b[1m\u001b[22m\u001b[2m │ gzip:  0.10 kB\u001b[22m\n\u001b[2mdist/\u001b[22m\u001b[35massets/index-IuJTBs0m.css                  \u001b[39m\u001b[1m\u001b[2m  0.14 kB\u001b[22m\u001b[1m\u001b[22m\u001b[2m │ gzip:  0.13 kB\u001b[22m\n\u001b[2mdist/\u001b[22m\u001b[35massets/el-space-3oFudasq.css               \u001b[39m\u001b[1m\u001b[2m  0.16 kB\u001b[22m\u001b[1m\u001b[22m\u001b[2m │ gzip:  0.12 kB\u001b[22m\n\u001b[2mdist/\u001b[22m\u001b[35massets/el-overlay-CUAhHdWP.css             \u001b[39m\u001b[1m\u001b[2m  0.18 kB\u001b[22m\u001b[1m\u001b[22m\u001b[2m │ gzip:  0.15 kB\u001b[22m\n\u001b[2mdist/\u001b[22m\u001b[35massets/index-i7qjKVjC.css                  \u001b[39m\u001b[1m\u001b[2m  0.19 kB\u001b[22m\u001b[1m\u001b[22m\u001b[2m │ gzip:  0.15 kB\u001b[22m\n\u001b[2mdist/\u001b[22m\u001b[35massets/index-DQlieogE.css                  \u001b[39m\u001b[1m\u001b[2m  0.19 kB\u001b[22m\u001b[1m\u001b[22m\u001b[2m │ gzip:  0.15 kB\u001b[22m\n\u001b[2mdist/\u001b[22m\u001b[35massets/index-Bs25LO5w.css                  \u001b[39m\u001b[1m\u001b[2m  0.21 kB\u001b[22m\u001b[1m\u001b[22m\u001b[2m │ gzip:  0.16 kB\u001b[22m\n\u001b[2mdist/\u001b[22m\u001b[35massets/index-DGgFaq3O.css                  \u001b[39m\u001b[1m\u001b[2m  0.21 kB\u001b[22m\u001b[1m\u001b[22m\u001b[2m │ gzip:  0.16 kB\u001b[22m\n\u001b[2mdist/\u001b[22m\u001b[35massets/CompactIdCell-DUkiVdF2.css          \u001b[39m\u001b[1m\u001b[2m  0.21 kB\u001b[22m\u001b[1m\u001b[22m\u001b[2m │ gzip:  0.18 kB\u001b[22m\n\u001b[2mdist/\u001b[22m\u001b[35massets/index-BB_vIipW.css                  \u001b[39m\u001b[1m\u001b[2m  0.24 kB\u001b[22m\u001b[1m\u001b[22m\u001b[2m │ gzip:  0.16 kB\u001b[22m\n\u001b[2mdist/\u001b[22m\u001b[35massets/index-DLNnQ4J_.css                  \u001b[39m\u001b[1m\u001b[2m  0.25 kB\u001b[22m\u001b[1m\u001b[22m\u001b[2m │ gzip:  0.17 kB\u001b[22m\n\u001b[2mdist/\u001b[22m\u001b[35massets/OrderLogisticsDrawer-o7Knf5Gg.css   \u001b[39m\u001b[1m\u001b[2m  0.29 kB\u001b[22m\u001b[1m\u001b[22m\u001b[2m │ gzip:  0.20 kB\u001b[22m\n\u001b[2mdist/\u001b[22m\u001b[35massets/index-DCu3G8Vr.css                  \u001b[39m\u001b[1m\u001b[2m  0.35 kB\u001b[22m\u001b[1m\u001b[22m\u001b[2m │ gzip:  0.21 kB\u001b[22m\n\u001b[2mdist/\u001b[22m\u001b[35massets/index-CXce6qjm.css                  \u001b[39m\u001b[1m\u001b[2m  0.36 kB\u001b[22m\u001b[1m\u001b[22m\u001b[2m │ gzip:  0.25 kB\u001b[22m\n\u001b[2mdist/\u001b[22m\u001b[35massets/index-CZsWzZ3t.css                  \u001b[39m\u001b[1m\u001b[2m  0.38 kB\u001b[22m\u001b[1m\u001b[22m\u001b[2m │ gzip:  0.22 kB\u001b[22m\n\u001b[2mdist/\u001b[22m\u001b[35massets/index-C6i0iFpM.css                  \u001b[39m\u001b[1m\u001b[2m  0.38 kB\u001b[22m\u001b[1m\u001b[22m\u001b[2m │ gzip:  0.22 kB\u001b[22m\n\u001b[2mdist/\u001b[22m\u001b[35massets/index-CcTVtgwf.css                  \u001b[39m\u001b[1m\u001b[2m  0.41 kB\u001b[22m\u001b[1m\u001b[22m\u001b[2m │ gzip:  0.23 kB\u001b[22m\n\u001b[2mdist/\u001b[22m\u001b[35massets/index-BOs1qe8I.css                  \u001b[39m\u001b[1m\u001b[2m  0.42 kB\u001b[22m\u001b[1m\u001b[22m\u001b[2m │ gzip:  0.24 kB\u001b[22m\n\u001b[2mdist/\u001b[22m\u001b[35massets/UserConfirmDialog-Cp9BtijX.css      \u001b[39m\u001b[1m\u001b[2m  0.46 kB\u001b[22m\u001b[1m\u001b[22m\u001b[2m │ gzip:  0.26 kB\u001b[22m\n\u001b[2mdist/\u001b[22m\u001b[35massets/index-DvVa3w6c.css                  \u001b[39m\u001b[1m\u001b[2m  0.70 kB\u001b[22m\u001b[1m\u001b[22m\u001b[2m │ gzip:  0.34 kB\u001b[22m\n\u001b[2mdist/\u001b[22m\u001b[35massets/el-divider-BUtF_RGI.css             \u001b[39m\u001b[1m\u001b[2m  0.71 kB\u001b[22m\u001b[1m\u001b[22m\u001b[2m │ gzip:  0.31 kB\u001b[22m\n\u001b[2mdist/\u001b[22m\u001b[35massets/el-avatar-BmRr_O8d.css              \u001b[39m\u001b[1m\u001b[2m  0.88 kB\u001b[22m\u001b[1m\u001b[22m\u001b[2m │ gzip:  0.34 kB\u001b[22m\n\u001b[2mdist/\u001b[22m\u001b[35massets/index-CwB0ktMY.css                  \u001b[39m\u001b[1m\u001b[2m  0.88 kB\u001b[22m\u001b[1m\u001b[22m\u001b[2m │ gzip:  0.36 kB\u001b[22m\n\u001b[2mdist/\u001b[22m\u001b[35massets/el-card-DGFn2Dlf.css                \u001b[39m\u001b[1m\u001b[2m  0.92 kB\u001b[22m\u001b[1m\u001b[22m\u001b[2m │ gzip:  0.33 kB\u001b[22m\n\u001b[2mdist/\u001b[22m\u001b[35massets/ContentBlockEditor-lHkBL_E-.css     \u001b[39m\u001b[1m\u001b[2m  0.99 kB\u001b[22m\u001b[1m\u001b[22m\u001b[2m │ gzip:  0.37 kB\u001b[22m\n\u001b[2mdist/\u001b[22m\u001b[35massets/index-DHb4KAKN.css                  \u001b[39m\u001b[1m\u001b[2m  1.04 kB\u001b[22m\u001b[1m\u001b[22m\u001b[2m │ gzip:  0.41 kB\u001b[22m\n\u001b[2mdist/\u001b[22m\u001b[35massets/el-empty-D4ZqTl4F.css               \u001b[39m\u001b[1m\u001b[2m  1.20 kB\u001b[22m\u001b[1m\u001b[22m\u001b[2m │ gzip:  0.47 kB\u001b[22m\n\u001b[2mdist/\u001b[22m\u001b[35massets/index-ny6BUt9x.css                  \u001b[39m\u001b[1m\u001b[2m  1.22 kB\u001b[22m\u001b[1m\u001b[22m\u001b[2m │ gzip:  0.49 kB\u001b[22m\n\u001b[2mdist/\u001b[22m\u001b[35massets/el-badge-BWN_0xb6.css               \u001b[39m\u001b[1m\u001b[2m  1.27 kB\u001b[22m\u001b[1m\u001b[22m\u001b[2m │ gzip:  0.47 kB\u001b[22m\n\u001b[2mdist/\u001b[22m\u001b[35massets/index-fNbH5sYx.css                  \u001b[39m\u001b[1m\u001b[2m  1.31 kB\u001b[22m\u001b[1m\u001b[22m\u001b[2m │ gzip:  0.51 kB\u001b[22m\n\u001b[2mdist/\u001b[22m\u001b[35massets/el-popover-Dx7EGtyB.css             \u001b[39m\u001b[1m\u001b[2m  1.53 kB\u001b[22m\u001b[1m\u001b[22m\u001b[2m │ gzip:  0.49 kB\u001b[22m\n\u001b[2mdist/\u001b[22m\u001b[35massets/el-loading-BGx_81yz.css             \u001b[39m\u001b[1m\u001b[2m  1.61 kB\u001b[22m\u001b[1m\u001b[22m\u001b[2m │ gzip:  0.55 kB\u001b[22m\n\u001b[2mdist/\u001b[22m\u001b[35massets/MediaPicker-C0M8FM_4.css            \u001b[39m\u001b[1m\u001b[2m  1.95 kB\u001b[22m\u001b[1m\u001b[22m\u001b[2m │ gzip:  0.72 kB\u001b[22m\n\u001b[2mdist/\u001b[22m\u001b[35massets/index-DZkNk_rH.css                  \u001b[39m\u001b[1m\u001b[2m  2.17 kB\u001b[22m\u001b[1m\u001b[22m\u001b[2m │ gzip:  0.68 kB\u001b[22m\n\u001b[2mdist/\u001b[22m\u001b[35massets/index-DjFk-SxH.css                  \u001b[39m\u001b[1m\u001b[2m  2.39 kB\u001b[22m\u001b[1m\u001b[22m\u001b[2m │ gzip:  0.83 kB\u001b[22m\n\u001b[2mdist/\u001b[22m\u001b[35massets/OrderDetailDrawer-DRQzNWnI.css      \u001b[39m\u001b[1m\u001b[2m  2.52 kB\u001b[22m\u001b[1m\u001b[22m\u001b[2m │ gzip:  0.74 kB\u001b[22m\n\u001b[2mdist/\u001b[22m\u001b[35massets/el-progress-Dw9yTa91.css            \u001b[39m\u001b[1m\u001b[2m  2.59 kB\u001b[22m\u001b[1m\u001b[22m\u001b[2m │ gzip:  0.76 kB\u001b[22m\n\u001b[2mdist/\u001b[22m\u001b[35massets/index-DVOIXb56.css                  \u001b[39m\u001b[1m\u001b[2m  2.68 kB\u001b[22m\u001b[1m\u001b[22m\u001b[2m │ gzip:  0.87 kB\u001b[22m\n\u001b[2mdist/\u001b[22m\u001b[35massets/el-image-viewer-BoL2ViNC.css        \u001b[39m\u001b[1m\u001b[2m  2.69 kB\u001b[22m\u001b[1m\u001b[22m\u001b[2m │ gzip:  0.82 kB\u001b[22m\n\u001b[2mdist/\u001b[22m\u001b[35massets/el-radio-button-CJN8lCDv.css        \u001b[39m\u001b[1m\u001b[2m  3.20 kB\u001b[22m\u001b[1m\u001b[22m\u001b[2m │ gzip:  0.77 kB\u001b[22m\n\u001b[2mdist/\u001b[22m\u001b[35massets/el-descriptions-item-o9ObloqJ.css   \u001b[39m\u001b[1m\u001b[2m  3.42 kB\u001b[22m\u001b[1m\u001b[22m\u001b[2m │ gzip:  0.60 kB\u001b[22m\n\u001b[2mdist/\u001b[22m\u001b[35massets/el-alert-G57rL0jl.css               \u001b[39m\u001b[1m\u001b[2m  3.46 kB\u001b[22m\u001b[1m\u001b[22m\u001b[2m │ gzip:  0.75 kB\u001b[22m\n\u001b[2mdist/\u001b[22m\u001b[35massets/el-drawer-_HV3aT0D.css              \u001b[39m\u001b[1m\u001b[2m  3.62 kB\u001b[22m\u001b[1m\u001b[22m\u001b[2m │ gzip:  0.92 kB\u001b[22m\n\u001b[2mdist/\u001b[22m\u001b[35massets/el-dialog-BvLOZX34.css              \u001b[39m\u001b[1m\u001b[2m  3.63 kB\u001b[22m\u001b[1m\u001b[22m\u001b[2m │ gzip:  1.00 kB\u001b[22m\n\u001b[2mdist/\u001b[22m\u001b[35massets/el-scrollbar-dPQ2-wqA.css           \u001b[39m\u001b[1m\u001b[2m  3.78 kB\u001b[22m\u001b[1m\u001b[22m\u001b[2m │ gzip:  0.89 kB\u001b[22m\n\u001b[2mdist/\u001b[22m\u001b[35massets/index-Dr78BW_q.css                  \u001b[39m\u001b[1m\u001b[2m  3.85 kB\u001b[22m\u001b[1m\u001b[22m\u001b[2m │ gzip:  0.99 kB\u001b[22m\n\u001b[2mdist/\u001b[22m\u001b[35massets/el-switch-BmTFCygm.css              \u001b[39m\u001b[1m\u001b[2m  3.93 kB\u001b[22m\u001b[1m\u001b[22m\u001b[2m │ gzip:  0.95 kB\u001b[22m\n\u001b[2mdist/\u001b[22m\u001b[35massets/index-D1lDNSR7.css                  \u001b[39m\u001b[1m\u001b[2m  3.99 kB\u001b[22m\u001b[1m\u001b[22m\u001b[2m │ gzip:  1.12 kB\u001b[22m\n\u001b[2mdist/\u001b[22m\u001b[35massets/index-CecAddHt.css                  \u001b[39m\u001b[1m\u001b[2m  4.01 kB\u001b[22m\u001b[1m\u001b[22m\u001b[2m │ gzip:  1.28 kB\u001b[22m\n\u001b[2mdist/\u001b[22m\u001b[35massets/index-BeiK9aHY.css                  \u001b[39m\u001b[1m\u001b[2m  4.25 kB\u001b[22m\u001b[1m\u001b[22m\u001b[2m │ gzip:  1.10 kB\u001b[22m\n\u001b[2mdist/\u001b[22m\u001b[35massets/el-input-number-D6iOyBgb.css        \u001b[39m\u001b[1m\u001b[2m  4.34 kB\u001b[22m\u001b[1m\u001b[22m\u001b[2m │ gzip:  0.91 kB\u001b[22m\n\u001b[2mdist/\u001b[22m\u001b[35massets/el-radio-9-RacdSu.css               \u001b[39m\u001b[1m\u001b[2m  4.35 kB\u001b[22m\u001b[1m\u001b[22m\u001b[2m │ gzip:  0.93 kB\u001b[22m\n\u001b[2mdist/\u001b[22m\u001b[35massets/el-timeline-item-BGwaItks.css       \u001b[39m\u001b[1m\u001b[2m  4.38 kB\u001b[22m\u001b[1m\u001b[22m\u001b[2m │ gzip:  0.86 kB\u001b[22m\n\u001b[2mdist/\u001b[22m\u001b[35massets/el-form-item-DdFfujyr.css           \u001b[39m\u001b[1m\u001b[2m  4.77 kB\u001b[22m\u001b[1m\u001b[22m\u001b[2m │ gzip:  0.90 kB\u001b[22m\n\u001b[2mdist/\u001b[22m\u001b[35massets/index-B7U5rxzS.css                  \u001b[39m\u001b[1m\u001b[2m  4.90 kB\u001b[22m\u001b[1m\u001b[22m\u001b[2m │ gzip:  1.08 kB\u001b[22m\n\u001b[2mdist/\u001b[22m\u001b[35massets/index-Rh6kpTOQ.css                  \u001b[39m\u001b[1m\u001b[2m  4.97 kB\u001b[22m\u001b[1m\u001b[22m\u001b[2m │ gzip:  1.36 kB\u001b[22m\n\u001b[2mdist/\u001b[22m\u001b[35massets/index-HmK2Y2n7.css                  \u001b[39m\u001b[1m\u001b[2m  5.68 kB\u001b[22m\u001b[1m\u001b[22m\u001b[2m │ gzip:  1.32 kB\u001b[22m\n\u001b[2mdist/\u001b[22m\u001b[35massets/el-tag-DjxZVOpb.css                 \u001b[39m\u001b[1m\u001b[2m  5.73 kB\u001b[22m\u001b[1m\u001b[22m\u001b[2m │ gzip:  0.95 kB\u001b[22m\n\u001b[2mdist/\u001b[22m\u001b[35massets/index-Cgh4Cm9X.css                  \u001b[39m\u001b[1m\u001b[2m  5.87 kB\u001b[22m\u001b[1m\u001b[22m\u001b[2m │ gzip:  1.35 kB\u001b[22m\n\u001b[2mdist/\u001b[22m\u001b[35massets/el-pagination-DvY-LlDT.css          \u001b[39m\u001b[1m\u001b[2m  6.92 kB\u001b[22m\u001b[1m\u001b[22m\u001b[2m │ gzip:  1.20 kB\u001b[22m\n\u001b[2mdist/\u001b[22m\u001b[35massets/index-CJa1MX4B.css                  \u001b[39m\u001b[1m\u001b[2m  7.25 kB\u001b[22m\u001b[1m\u001b[22m\u001b[2m │ gzip:  1.60 kB\u001b[22m\n\u001b[2mdist/\u001b[22m\u001b[35massets/el-color-picker-panel-ClJnORUF.css  \u001b[39m\u001b[1m\u001b[2m  7.27 kB\u001b[22m\u001b[1m\u001b[22m\u001b[2m │ gzip:  1.56 kB\u001b[22m\n\u001b[2mdist/\u001b[22m\u001b[35massets/base-D3TBFhuC.css                   \u001b[39m\u001b[1m\u001b[2m  8.16 kB\u001b[22m\u001b[1m\u001b[22m\u001b[2m │ gzip:  2.04 kB\u001b[22m\n\u001b[2mdist/\u001b[22m\u001b[35massets/index-CgTAlxIv.css                  \u001b[39m\u001b[1m\u001b[2m  8.78 kB\u001b[22m\u001b[1m\u001b[22m\u001b[2m │ gzip:  2.21 kB\u001b[22m\n\u001b[2mdist/\u001b[22m\u001b[35massets/el-select-CS5JQKo7.css              \u001b[39m\u001b[1m\u001b[2m  9.20 kB\u001b[22m\u001b[1m\u001b[22m\u001b[2m │ gzip:  1.93 kB\u001b[22m\n\u001b[2mdist/\u001b[22m\u001b[35massets/index-BRzpAOJr.css                  \u001b[39m\u001b[1m\u001b[2m 10.11 kB\u001b[22m\u001b[1m\u001b[22m\u001b[2m │ gzip:  2.16 kB\u001b[22m\n\u001b[2mdist/\u001b[22m\u001b[35massets/el-dropdown-item-DDiCq6Am.css       \u001b[39m\u001b[1m\u001b[2m 10.13 kB\u001b[22m\u001b[1m\u001b[22m\u001b[2m │ gzip:  1.41 kB\u001b[22m\n\u001b[2mdist/\u001b[22m\u001b[35massets/el-input-haxN-bjV.css               \u001b[39m\u001b[1m\u001b[2m 11.19 kB\u001b[22m\u001b[1m\u001b[22m\u001b[2m │ gzip:  1.79 kB\u001b[22m\n\u001b[2mdist/\u001b[22m\u001b[35massets/el-upload-sqBRi0zR.css              \u001b[39m\u001b[1m\u001b[2m 11.68 kB\u001b[22m\u001b[1m\u001b[22m\u001b[2m │ gzip:  2.08 kB\u001b[22m\n\u001b[2mdist/\u001b[22m\u001b[35massets/el-tab-pane-CnNoQHsR.css            \u001b[39m\u001b[1m\u001b[2m 14.92 kB\u001b[22m\u001b[1m\u001b[22m\u001b[2m │ gzip:  2.27 kB\u001b[22m\n\u001b[2mdist/\u001b[22m\u001b[35massets/el-button-DhOMi8yW.css              \u001b[39m\u001b[1m\u001b[2m 15.61 kB\u001b[22m\u001b[1m\u001b[22m\u001b[2m │ gzip:  1.94 kB\u001b[22m\n\u001b[2mdist/\u001b[22m\u001b[35massets/index-mmtln4kX.css                  \u001b[39m\u001b[1m\u001b[2m 16.39 kB\u001b[22m\u001b[1m\u001b[22m\u001b[2m │ gzip:  3.04 kB\u001b[22m\n\u001b[2mdist/\u001b[22m\u001b[35massets/el-table-column-BMyxChP6.css        \u001b[39m\u001b[1m\u001b[2m 26.13 kB\u001b[22m\u001b[1m\u001b[22m\u001b[2m │ gzip:  3.84 kB\u001b[22m\n\u001b[2mdist/\u001b[22m\u001b[35massets/el-date-picker-panel-C0naBazS.css   \u001b[39m\u001b[1m\u001b[2m 28.81 kB\u001b[22m\u001b[1m\u001b[22m\u001b[2m │ gzip:  4.17 kB\u001b[22m\n\u001b[2mdist/\u001b[22m\u001b[35massets/el-col-Ds2mGN2S.css                 \u001b[39m\u001b[1m\u001b[2m 39.17 kB\u001b[22m\u001b[1m\u001b[22m\u001b[2m │ gzip:  3.91 kB\u001b[22m\n\u001b[2mdist/\u001b[22m\u001b[35massets/index-XFU74PjQ.css                  \u001b[39m\u001b[1m\u001b[2m358.00 kB\u001b[22m\u001b[1m\u001b[22m\u001b[2m │ gzip: 49.49 kB\u001b[22m\n\u001b[2mdist/\u001b[22m\u001b[36massets/el-tooltip-l0sNRNKZ.js              \u001b[39m\u001b[1m\u001b[2m  0.00 kB\u001b[22m\u001b[1m\u001b[22m\u001b[2m │ gzip:  0.02 kB\u001b[22m\n\u001b[2mdist/\u001b[22m\u001b[36massets/validator-D7feto-m.js               \u001b[39m\u001b[1m\u001b[2m  0.09 kB\u001b[22m\u001b[1m\u001b[22m\u001b[2m │ gzip:  0.10 kB\u001b[22m\n\u001b[2mdist/\u001b[22m\u001b[36massets/usePagination-B4HNN0qo.js           \u001b[39m\u001b[1m\u001b[2m  0.31 kB\u001b[22m\u001b[1m\u001b[22m\u001b[2m │ gzip:  0.23 kB\u001b[22m\n\u001b[2mdist/\u001b[22m\u001b[36massets/userDisplay-C4kS6kdM.js             \u001b[39m\u001b[1m\u001b[2m  0.35 kB\u001b[22m\u001b[1m\u001b[22m\u001b[2m │ gzip:  0.20 kB\u001b[22m\n\u001b[2mdist/\u001b[22m\u001b[36massets/userRouting-CC1jxEzV.js             \u001b[39m\u001b[1m\u001b[2m  0.38 kB\u001b[22m\u001b[1m\u001b[22m\u001b[2m │ gzip:  0.24 kB\u001b[22m\n\u001b[2mdist/\u001b[22m\u001b[36massets/strings-GZVVbvID.js                 \u001b[39m\u001b[1m\u001b[2m  0.42 kB\u001b[22m\u001b[1m\u001b[22m\u001b[2m │ gzip:  0.29 kB\u001b[22m\n\u001b[2mdist/\u001b[22m\u001b[36massets/format-BJh4dPeo.js                  \u001b[39m\u001b[1m\u001b[2m  0.42 kB\u001b[22m\u001b[1m\u001b[22m\u001b[2m │ gzip:  0.28 kB\u001b[22m\n\u001b[2mdist/\u001b[22m\u001b[36massets/toNumber-CO6P1rwz.js                \u001b[39m\u001b[1m\u001b[2m  0.54 kB\u001b[22m\u001b[1m\u001b[22m\u001b[2m │ gzip:  0.36 kB\u001b[22m\n\u001b[2mdist/\u001b[22m\u001b[36massets/index-BfRpFAx8.js                   \u001b[39m\u001b[1m\u001b[2m  0.62 kB\u001b[22m\u001b[1m\u001b[22m\u001b[2m │ gzip:  0.39 kB\u001b[22m\n\u001b[2mdist/\u001b[22m\u001b[36massets/consistency-CI3hk9IF.js             \u001b[39m\u001b[1m\u001b[2m  0.76 kB\u001b[22m\u001b[1m\u001b[22m\u001b[2m │ gzip:  0.46 kB\u001b[22m\n\u001b[2mdist/\u001b[22m\u001b[36massets/el-divider-PwG-yZn_.js              \u001b[39m\u001b[1m\u001b[2m  0.80 kB\u001b[22m\u001b[1m\u001b[22m\u001b[2m │ gzip:  0.48 kB\u001b[22m\n\u001b[2mdist/\u001b[22m\u001b[36massets/index-BFNcM-cS.js                   \u001b[39m\u001b[1m\u001b[2m  0.98 kB\u001b[22m\u001b[1m\u001b[22m\u001b[2m │ gzip:  0.54 kB\u001b[22m\n\u001b[2mdist/\u001b[22m\u001b[36massets/catalog-Bu2gQMBb.js                 \u001b[39m\u001b[1m\u001b[2m  0.98 kB\u001b[22m\u001b[1m\u001b[22m\u001b[2m │ gzip:  0.32 kB\u001b[22m\n\u001b[2mdist/\u001b[22m\u001b[36massets/CompactIdCell-D6ZPSj9d.js           \u001b[39m\u001b[1m\u001b[2m  1.01 kB\u001b[22m\u001b[1m\u001b[22m\u001b[2m │ gzip:  0.56 kB\u001b[22m\n\u001b[2mdist/\u001b[22m\u001b[36massets/vnode-BVIO0aLv.js                   \u001b[39m\u001b[1m\u001b[2m  1.14 kB\u001b[22m\u001b[1m\u001b[22m\u001b[2m │ gzip:  0.61 kB\u001b[22m\n\u001b[2mdist/\u001b[22m\u001b[36massets/commission-BEbvqtsh.js              \u001b[39m\u001b[1m\u001b[2m  1.34 kB\u001b[22m\u001b[1m\u001b[22m\u001b[2m │ gzip:  0.66 kB\u001b[22m\n\u001b[2mdist/\u001b[22m\u001b[36massets/system-BLuZLGuT.js                  \u001b[39m\u001b[1m\u001b[2m  1.38 kB\u001b[22m\u001b[1m\u001b[22m\u001b[2m │ gzip:  0.49 kB\u001b[22m\n\u001b[2mdist/\u001b[22m\u001b[36massets/assetUrlAudit-CXyrdbJt.js           \u001b[39m\u001b[1m\u001b[2m  1.49 kB\u001b[22m\u001b[1m\u001b[22m\u001b[2m │ gzip:  0.76 kB\u001b[22m\n\u001b[2mdist/\u001b[22m\u001b[36massets/index-D2IyxZK6.js                   \u001b[39m\u001b[1m\u001b[2m  1.64 kB\u001b[22m\u001b[1m\u001b[22m\u001b[2m │ gzip:  0.56 kB\u001b[22m\n\u001b[2mdist/\u001b[22m\u001b[36massets/base-DyE3m2I6.js                    \u001b[39m\u001b[1m\u001b[2m  1.77 kB\u001b[22m\u001b[1m\u001b[22m\u001b[2m │ gzip:  0.88 kB\u001b[22m\n\u001b[2mdist/\u001b[22m\u001b[36massets/content-CpxuWnXL.js                 \u001b[39m\u001b[1m\u001b[2m  1.88 kB\u001b[22m\u001b[1m\u001b[22m\u001b[2m │ gzip:  0.52 kB\u001b[22m\n\u001b[2mdist/\u001b[22m\u001b[36massets/finance-DWSWegkj.js                 \u001b[39m\u001b[1m\u001b[2m  1.94 kB\u001b[22m\u001b[1m\u001b[22m\u001b[2m │ gzip:  0.57 kB\u001b[22m\n\u001b[2mdist/\u001b[22m\u001b[36massets/el-alert-BAnNAUuC.js                \u001b[39m\u001b[1m\u001b[2m  2.00 kB\u001b[22m\u001b[1m\u001b[22m\u001b[2m │ gzip:  0.95 kB\u001b[22m\n\u001b[2mdist/\u001b[22m\u001b[36massets/el-tag-Y9P6tPG9.js                  \u001b[39m\u001b[1m\u001b[2m  2.06 kB\u001b[22m\u001b[1m\u001b[22m\u001b[2m │ gzip:  0.94 kB\u001b[22m\n\u001b[2mdist/\u001b[22m\u001b[36massets/el-col-BfDJuYbc.js                  \u001b[39m\u001b[1m\u001b[2m  2.08 kB\u001b[22m\u001b[1m\u001b[22m\u001b[2m │ gzip:  0.87 kB\u001b[22m\n\u001b[2mdist/\u001b[22m\u001b[36massets/users-B-GXFgV0.js                   \u001b[39m\u001b[1m\u001b[2m  2.10 kB\u001b[22m\u001b[1m\u001b[22m\u001b[2m │ gzip:  0.69 kB\u001b[22m\n\u001b[2mdist/\u001b[22m\u001b[36massets/el-timeline-item-BjLw3Z73.js        \u001b[39m\u001b[1m\u001b[2m  2.15 kB\u001b[22m\u001b[1m\u001b[22m\u001b[2m │ gzip:  0.96 kB\u001b[22m\n\u001b[2mdist/\u001b[22m\u001b[36massets/debounce-C12Ia0jy.js                \u001b[39m\u001b[1m\u001b[2m  2.20 kB\u001b[22m\u001b[1m\u001b[22m\u001b[2m │ gzip:  1.07 kB\u001b[22m\n\u001b[2mdist/\u001b[22m\u001b[36massets/partners-JOQ2QtrF.js                \u001b[39m\u001b[1m\u001b[2m  2.47 kB\u001b[22m\u001b[1m\u001b[22m\u001b[2m │ gzip:  0.63 kB\u001b[22m\n\u001b[2mdist/\u001b[22m\u001b[36massets/el-card-Cct1ZI8F.js                 \u001b[39m\u001b[1m\u001b[2m  2.57 kB\u001b[22m\u001b[1m\u001b[22m\u001b[2m │ gzip:  1.26 kB\u001b[22m\n\u001b[2mdist/\u001b[22m\u001b[36massets/el-space-CDSTdu89.js                \u001b[39m\u001b[1m\u001b[2m  2.60 kB\u001b[22m\u001b[1m\u001b[22m\u001b[2m │ gzip:  1.26 kB\u001b[22m\n\u001b[2mdist/\u001b[22m\u001b[36massets/mediaUpload-B5Te6UUY.js             \u001b[39m\u001b[1m\u001b[2m  2.65 kB\u001b[22m\u001b[1m\u001b[22m\u001b[2m │ gzip:  1.55 kB\u001b[22m\n\u001b[2mdist/\u001b[22m\u001b[36massets/el-avatar-AxiNfQfj.js               \u001b[39m\u001b[1m\u001b[2m  2.84 kB\u001b[22m\u001b[1m\u001b[22m\u001b[2m │ gzip:  1.31 kB\u001b[22m\n\u001b[2mdist/\u001b[22m\u001b[36massets/miniProgramTargets-Da4LaYJC.js      \u001b[39m\u001b[1m\u001b[2m  2.93 kB\u001b[22m\u001b[1m\u001b[22m\u001b[2m │ gzip:  1.25 kB\u001b[22m\n\u001b[2mdist/\u001b[22m\u001b[36massets/el-popover-C4RIuCkq.js              \u001b[39m\u001b[1m\u001b[2m  2.94 kB\u001b[22m\u001b[1m\u001b[22m\u001b[2m │ gzip:  1.29 kB\u001b[22m\n\u001b[2mdist/\u001b[22m\u001b[36massets/marketing-CWJkRW83.js               \u001b[39m\u001b[1m\u001b[2m  3.24 kB\u001b[22m\u001b[1m\u001b[22m\u001b[2m │ gzip:  0.84 kB\u001b[22m\n\u001b[2mdist/\u001b[22m\u001b[36massets/index--shMB0TW.js                   \u001b[39m\u001b[1m\u001b[2m  3.29 kB\u001b[22m\u001b[1m\u001b[22m\u001b[2m │ gzip:  1.59 kB\u001b[22m\n\u001b[2mdist/\u001b[22m\u001b[36massets/OrderLogisticsDrawer-B67XojJB.js    \u001b[39m\u001b[1m\u001b[2m  3.57 kB\u001b[22m\u001b[1m\u001b[22m\u001b[2m │ gzip:  1.67 kB\u001b[22m\n\u001b[2mdist/\u001b[22m\u001b[36massets/UserConfirmDialog-CQM_ZEMd.js       \u001b[39m\u001b[1m\u001b[2m  3.72 kB\u001b[22m\u001b[1m\u001b[22m\u001b[2m │ gzip:  1.96 kB\u001b[22m\n\u001b[2mdist/\u001b[22m\u001b[36massets/index-DN7kpdSK.js                   \u001b[39m\u001b[1m\u001b[2m  4.27 kB\u001b[22m\u001b[1m\u001b[22m\u001b[2m │ gzip:  2.06 kB\u001b[22m\n\u001b[2mdist/\u001b[22m\u001b[36massets/index-bGblPUVv.js                   \u001b[39m\u001b[1m\u001b[2m  4.30 kB\u001b[22m\u001b[1m\u001b[22m\u001b[2m │ gzip:  1.95 kB\u001b[22m\n\u001b[2mdist/\u001b[22m\u001b[36massets/el-overlay-CfVIVAmR.js              \u001b[39m\u001b[1m\u001b[2m  4.38 kB\u001b[22m\u001b[1m\u001b[22m\u001b[2m │ gzip:  1.74 kB\u001b[22m\n\u001b[2mdist/\u001b[22m\u001b[36massets/el-progress-DsRHEGSp.js             \u001b[39m\u001b[1m\u001b[2m  4.43 kB\u001b[22m\u001b[1m\u001b[22m\u001b[2m │ gzip:  1.84 kB\u001b[22m\n\u001b[2mdist/\u001b[22m\u001b[36massets/el-empty-CoG9laN5.js                \u001b[39m\u001b[1m\u001b[2m  4.48 kB\u001b[22m\u001b[1m\u001b[22m\u001b[2m │ gzip:  1.62 kB\u001b[22m\n\u001b[2mdist/\u001b[22m\u001b[36massets/index-DOBHXCFP.js                   \u001b[39m\u001b[1m\u001b[2m  4.83 kB\u001b[22m\u001b[1m\u001b[22m\u001b[2m │ gzip:  2.18 kB\u001b[22m\n\u001b[2mdist/\u001b[22m\u001b[36massets/el-descriptions-item-CUvBArhb.js    \u001b[39m\u001b[1m\u001b[2m  4.84 kB\u001b[22m\u001b[1m\u001b[22m\u001b[2m │ gzip:  1.92 kB\u001b[22m\n\u001b[2mdist/\u001b[22m\u001b[36massets/el-dialog-DYwgUWEH.js               \u001b[39m\u001b[1m\u001b[2m  4.85 kB\u001b[22m\u001b[1m\u001b[22m\u001b[2m │ gzip:  2.10 kB\u001b[22m\n\u001b[2mdist/\u001b[22m\u001b[36massets/el-loading-CuAWNLaP.js              \u001b[39m\u001b[1m\u001b[2m  4.88 kB\u001b[22m\u001b[1m\u001b[22m\u001b[2m │ gzip:  2.09 kB\u001b[22m\n\u001b[2mdist/\u001b[22m\u001b[36massets/el-switch-CQUM2XtM.js               \u001b[39m\u001b[1m\u001b[2m  5.10 kB\u001b[22m\u001b[1m\u001b[22m\u001b[2m │ gzip:  1.76 kB\u001b[22m\n\u001b[2mdist/\u001b[22m\u001b[36massets/el-drawer-Crj9ZCfz.js               \u001b[39m\u001b[1m\u001b[2m  5.20 kB\u001b[22m\u001b[1m\u001b[22m\u001b[2m │ gzip:  2.35 kB\u001b[22m\n\u001b[2mdist/\u001b[22m\u001b[36massets/el-radio-iMjAq9PC.js                \u001b[39m\u001b[1m\u001b[2m  5.49 kB\u001b[22m\u001b[1m\u001b[22m\u001b[2m │ gzip:  2.24 kB\u001b[22m\n\u001b[2mdist/\u001b[22m\u001b[36massets/index-BTndmnuO.js                   \u001b[39m\u001b[1m\u001b[2m  5.51 kB\u001b[22m\u001b[1m\u001b[22m\u001b[2m │ gzip:  2.28 kB\u001b[22m\n\u001b[2mdist/\u001b[22m\u001b[36massets/index-C4XyQDLj.js                   \u001b[39m\u001b[1m\u001b[2m  5.62 kB\u001b[22m\u001b[1m\u001b[22m\u001b[2m │ gzip:  2.42 kB\u001b[22m\n\u001b[2mdist/\u001b[22m\u001b[36massets/MediaPicker-Becsae3-.js             \u001b[39m\u001b[1m\u001b[2m  6.42 kB\u001b[22m\u001b[1m\u001b[22m\u001b[2m │ gzip:  3.28 kB\u001b[22m\n\u001b[2mdist/\u001b[22m\u001b[36massets/index-B_RYWTKg.js                   \u001b[39m\u001b[1m\u001b[2m  6.72 kB\u001b[22m\u001b[1m\u001b[22m\u001b[2m │ gzip:  3.01 kB\u001b[22m\n\u001b[2mdist/\u001b[22m\u001b[36massets/el-input-number-Dcmsn-jZ.js         \u001b[39m\u001b[1m\u001b[2m  6.86 kB\u001b[22m\u001b[1m\u001b[22m\u001b[2m │ gzip:  2.78 kB\u001b[22m\n\u001b[2mdist/\u001b[22m\u001b[36massets/index-Ch9ZzMDj.js                   \u001b[39m\u001b[1m\u001b[2m  7.07 kB\u001b[22m\u001b[1m\u001b[22m\u001b[2m │ gzip:  3.18 kB\u001b[22m\n\u001b[2mdist/\u001b[22m\u001b[36massets/dayjs.min-Bof1u0Bp.js               \u001b[39m\u001b[1m\u001b[2m  7.28 kB\u001b[22m\u001b[1m\u001b[22m\u001b[2m │ gzip:  3.16 kB\u001b[22m\n\u001b[2mdist/\u001b[22m\u001b[36massets/index-DlHCaxym.js                   \u001b[39m\u001b[1m\u001b[2m  7.51 kB\u001b[22m\u001b[1m\u001b[22m\u001b[2m │ gzip:  3.22 kB\u001b[22m\n\u001b[2mdist/\u001b[22m\u001b[36massets/aria-C1zK9Cfm.js                    \u001b[39m\u001b[1m\u001b[2m  7.91 kB\u001b[22m\u001b[1m\u001b[22m\u001b[2m │ gzip:  3.32 kB\u001b[22m\n\u001b[2mdist/\u001b[22m\u001b[36massets/OrderMutationDialogs-Cx8FaYmg.js    \u001b[39m\u001b[1m\u001b[2m  8.26 kB\u001b[22m\u001b[1m\u001b[22m\u001b[2m │ gzip:  2.95 kB\u001b[22m\n\u001b[2mdist/\u001b[22m\u001b[36massets/index-DLCvzLgA.js                   \u001b[39m\u001b[1m\u001b[2m  8.35 kB\u001b[22m\u001b[1m\u001b[22m\u001b[2m │ gzip:  3.33 kB\u001b[22m\n\u001b[2mdist/\u001b[22m\u001b[36massets/index-BVF-uzlh.js                   \u001b[39m\u001b[1m\u001b[2m  8.97 kB\u001b[22m\u001b[1m\u001b[22m\u001b[2m │ gzip:  3.95 kB\u001b[22m\n\u001b[2mdist/\u001b[22m\u001b[36massets/index-3ktqrhSj.js                   \u001b[39m\u001b[1m\u001b[2m  9.24 kB\u001b[22m\u001b[1m\u001b[22m\u001b[2m │ gzip:  4.00 kB\u001b[22m\n\u001b[2mdist/\u001b[22m\u001b[36massets/index-DS5F4zNZ.js                   \u001b[39m\u001b[1m\u001b[2m 10.09 kB\u001b[22m\u001b[1m\u001b[22m\u001b[2m │ gzip:  4.40 kB\u001b[22m\n\u001b[2mdist/\u001b[22m\u001b[36massets/el-tab-pane-CJm4aVjB.js             \u001b[39m\u001b[1m\u001b[2m 11.49 kB\u001b[22m\u001b[1m\u001b[22m\u001b[2m │ gzip:  4.85 kB\u001b[22m\n\u001b[2mdist/\u001b[22m\u001b[36massets/index-DIN53fEO.js                   \u001b[39m\u001b[1m\u001b[2m 11.49 kB\u001b[22m\u001b[1m\u001b[22m\u001b[2m │ gzip:  4.29 kB\u001b[22m\n\u001b[2mdist/\u001b[22m\u001b[36massets/el-image-viewer-DmQKAMbG.js         \u001b[39m\u001b[1m\u001b[2m 11.57 kB\u001b[22m\u001b[1m\u001b[22m\u001b[2m │ gzip:  4.42 kB\u001b[22m\n\u001b[2mdist/\u001b[22m\u001b[36massets/index-BjRV_nn8.js                   \u001b[39m\u001b[1m\u001b[2m 11.81 kB\u001b[22m\u001b[1m\u001b[22m\u001b[2m │ gzip:  4.85 kB\u001b[22m\n\u001b[2mdist/\u001b[22m\u001b[36massets/el-pagination-Cg_kGIEO.js           \u001b[39m\u001b[1m\u001b[2m 11.91 kB\u001b[22m\u001b[1m\u001b[22m\u001b[2m │ gzip:  4.11 kB\u001b[22m\n\u001b[2mdist/\u001b[22m\u001b[36massets/index-CRjfSxMk.js                   \u001b[39m\u001b[1m\u001b[2m 11.97 kB\u001b[22m\u001b[1m\u001b[22m\u001b[2m │ gzip:  4.72 kB\u001b[22m\n\u001b[2mdist/\u001b[22m\u001b[36massets/index-CeRpmQ_N.js                   \u001b[39m\u001b[1m\u001b[2m 12.42 kB\u001b[22m\u001b[1m\u001b[22m\u001b[2m │ gzip:  4.18 kB\u001b[22m\n\u001b[2mdist/\u001b[22m\u001b[36massets/ContentBlockEditor-B5CVK8qk.js      \u001b[39m\u001b[1m\u001b[2m 12.60 kB\u001b[22m\u001b[1m\u001b[22m\u001b[2m │ gzip:  4.78 kB\u001b[22m\n\u001b[2mdist/\u001b[22m\u001b[36massets/index-ASvwU5Ka.js                   \u001b[39m\u001b[1m\u001b[2m 12.61 kB\u001b[22m\u001b[1m\u001b[22m\u001b[2m │ gzip:  5.14 kB\u001b[22m\n\u001b[2mdist/\u001b[22m\u001b[36massets/el-input-CR0u8zn7.js                \u001b[39m\u001b[1m\u001b[2m 13.79 kB\u001b[22m\u001b[1m\u001b[22m\u001b[2m │ gzip:  5.05 kB\u001b[22m\n\u001b[2mdist/\u001b[22m\u001b[36massets/el-upload-B83xa8_J.js               \u001b[39m\u001b[1m\u001b[2m 14.23 kB\u001b[22m\u001b[1m\u001b[22m\u001b[2m │ gzip:  5.22 kB\u001b[22m\n\u001b[2mdist/\u001b[22m\u001b[36massets/index-nkFauMwh.js                   \u001b[39m\u001b[1m\u001b[2m 14.24 kB\u001b[22m\u001b[1m\u001b[22m\u001b[2m │ gzip:  5.59 kB\u001b[22m\n\u001b[2mdist/\u001b[22m\u001b[36massets/OrderDetailDrawer-DZ6zfqZ4.js       \u001b[39m\u001b[1m\u001b[2m 14.31 kB\u001b[22m\u001b[1m\u001b[22m\u001b[2m │ gzip:  4.36 kB\u001b[22m\n\u001b[2mdist/\u001b[22m\u001b[36massets/index-BCIXn4W7.js                   \u001b[39m\u001b[1m\u001b[2m 14.56 kB\u001b[22m\u001b[1m\u001b[22m\u001b[2m │ gzip:  5.92 kB\u001b[22m\n\u001b[2mdist/\u001b[22m\u001b[36massets/index-C63gCXoh.js                   \u001b[39m\u001b[1m\u001b[2m 14.75 kB\u001b[22m\u001b[1m\u001b[22m\u001b[2m │ gzip:  5.50 kB\u001b[22m\n\u001b[2mdist/\u001b[22m\u001b[36massets/el-dropdown-item-k4M00-YP.js        \u001b[39m\u001b[1m\u001b[2m 15.22 kB\u001b[22m\u001b[1m\u001b[22m\u001b[2m │ gzip:  5.45 kB\u001b[22m\n\u001b[2mdist/\u001b[22m\u001b[36massets/index-C21yKiTs.js                   \u001b[39m\u001b[1m\u001b[2m 15.63 kB\u001b[22m\u001b[1m\u001b[22m\u001b[2m │ gzip:  5.76 kB\u001b[22m\n\u001b[2mdist/\u001b[22m\u001b[36massets/index-Uyt_MEfJ.js                   \u001b[39m\u001b[1m\u001b[2m 16.68 kB\u001b[22m\u001b[1m\u001b[22m\u001b[2m │ gzip:  5.83 kB\u001b[22m\n\u001b[2mdist/\u001b[22m\u001b[36massets/index-xO0-eCkA.js                   \u001b[39m\u001b[1m\u001b[2m 16.97 kB\u001b[22m\u001b[1m\u001b[22m\u001b[2m │ gzip:  7.03 kB\u001b[22m\n\u001b[2mdist/\u001b[22m\u001b[36massets/index-C9AhX1Dg.js                   \u001b[39m\u001b[1m\u001b[2m 17.93 kB\u001b[22m\u001b[1m\u001b[22m\u001b[2m │ gzip:  7.08 kB\u001b[22m\n\u001b[2mdist/\u001b[22m\u001b[36massets/index-BlGjYNky.js                   \u001b[39m\u001b[1m\u001b[2m 18.05 kB\u001b[22m\u001b[1m\u001b[22m\u001b[2m │ gzip:  6.21 kB\u001b[22m\n\u001b[2mdist/\u001b[22m\u001b[36massets/el-button-CGxY0wnH.js               \u001b[39m\u001b[1m\u001b[2m 19.81 kB\u001b[22m\u001b[1m\u001b[22m\u001b[2m │ gzip:  6.95 kB\u001b[22m\n\u001b[2mdist/\u001b[22m\u001b[36massets/el-color-picker-panel-CzX0rqUK.js   \u001b[39m\u001b[1m\u001b[2m 19.93 kB\u001b[22m\u001b[1m\u001b[22m\u001b[2m │ gzip:  6.83 kB\u001b[22m\n\u001b[2mdist/\u001b[22m\u001b[36massets/index-CSs3UIJl.js                   \u001b[39m\u001b[1m\u001b[2m 23.15 kB\u001b[22m\u001b[1m\u001b[22m\u001b[2m │ gzip:  7.88 kB\u001b[22m\n\u001b[2mdist/\u001b[22m\u001b[36massets/index-DDWOH4YM.js                   \u001b[39m\u001b[1m\u001b[2m 25.97 kB\u001b[22m\u001b[1m\u001b[22m\u001b[2m │ gzip:  8.14 kB\u001b[22m\n\u001b[2mdist/\u001b[22m\u001b[36massets/el-form-item-D0KwPsfH.js            \u001b[39m\u001b[1m\u001b[2m 26.99 kB\u001b[22m\u001b[1m\u001b[22m\u001b[2m │ gzip:  9.38 kB\u001b[22m\n\u001b[2mdist/\u001b[22m\u001b[36massets/panel-time-pick.vue2-BV_nkqmo.js    \u001b[39m\u001b[1m\u001b[2m 27.07 kB\u001b[22m\u001b[1m\u001b[22m\u001b[2m │ gzip: 10.20 kB\u001b[22m\n\u001b[2mdist/\u001b[22m\u001b[36massets/index-BBRgpKok.js                   \u001b[39m\u001b[1m\u001b[2m 27.56 kB\u001b[22m\u001b[1m\u001b[22m\u001b[2m │ gzip:  9.47 kB\u001b[22m\n\u001b[2mdist/\u001b[22m\u001b[36massets/index-DR8O5ecf.js                   \u001b[39m\u001b[1m\u001b[2m 28.35 kB\u001b[22m\u001b[1m\u001b[22m\u001b[2m │ gzip: 10.09 kB\u001b[22m\n\u001b[2mdist/\u001b[22m\u001b[36massets/el-select-BDp-x2Lo.js               \u001b[39m\u001b[1m\u001b[2m 30.29 kB\u001b[22m\u001b[1m\u001b[22m\u001b[2m │ gzip: 10.38 kB\u001b[22m\n\u001b[2mdist/\u001b[22m\u001b[36massets/index-CHWtginp.js                   \u001b[39m\u001b[1m\u001b[2m 33.32 kB\u001b[22m\u001b[1m\u001b[22m\u001b[2m │ gzip: 12.29 kB\u001b[22m\n\u001b[2mdist/\u001b[22m\u001b[36massets/http-vendor-C0Zqfgkc.js             \u001b[39m\u001b[1m\u001b[2m 36.62 kB\u001b[22m\u001b[1m\u001b[22m\u001b[2m │ gzip: 14.72 kB\u001b[22m\n\u001b[2mdist/\u001b[22m\u001b[36massets/index-elD5X4C_.js                   \u001b[39m\u001b[1m\u001b[2m 40.78 kB\u001b[22m\u001b[1m\u001b[22m\u001b[2m │ gzip: 13.07 kB\u001b[22m\n\u001b[2mdist/\u001b[22m\u001b[36massets/index-C5tL-GAS.js                   \u001b[39m\u001b[1m\u001b[2m 45.68 kB\u001b[22m\u001b[1m\u001b[22m\u001b[2m │ gzip: 14.25 kB\u001b[22m\n\u001b[2mdist/\u001b[22m\u001b[36massets/element-plus-icons-B-gE_hao.js      \u001b[39m\u001b[1m\u001b[2m 45.82 kB\u001b[22m\u001b[1m\u001b[22m\u001b[2m │ gzip: 11.33 kB\u001b[22m\n\u001b[2mdist/\u001b[22m\u001b[36massets/index-Db_O8N05.js                   \u001b[39m\u001b[1m\u001b[2m 46.80 kB\u001b[22m\u001b[1m\u001b[22m\u001b[2m │ gzip: 16.39 kB\u001b[22m\n\u001b[2mdist/\u001b[22m\u001b[36massets/el-scrollbar-BFn-donh.js            \u001b[39m\u001b[1m\u001b[2m 52.51 kB\u001b[22m\u001b[1m\u001b[22m\u001b[2m │ gzip: 18.52 kB\u001b[22m\n\u001b[2mdist/\u001b[22m\u001b[36massets/index-DvGgnOcK.js                   \u001b[39m\u001b[1m\u001b[2m 55.46 kB\u001b[22m\u001b[1m\u001b[22m\u001b[2m │ gzip: 15.76 kB\u001b[22m\n\u001b[2mdist/\u001b[22m\u001b[36massets/index-CPwYBxAs.js                   \u001b[39m\u001b[1m\u001b[2m 62.26 kB\u001b[22m\u001b[1m\u001b[22m\u001b[2m │ gzip: 18.89 kB\u001b[22m\n\u001b[2mdist/\u001b[22m\u001b[36massets/el-date-picker-panel-Dgbsesr-.js    \u001b[39m\u001b[1m\u001b[2m 64.78 kB\u001b[22m\u001b[1m\u001b[22m\u001b[2m │ gzip: 17.53 kB\u001b[22m\n\u001b[2mdist/\u001b[22m\u001b[36massets/index-BGtjYQCV.js                   \u001b[39m\u001b[1m\u001b[2m 74.15 kB\u001b[22m\u001b[1m\u001b[22m\u001b[2m │ gzip: 27.32 kB\u001b[22m\n\u001b[2mdist/\u001b[22m\u001b[36massets/el-table-column-D9e8BPQX.js         \u001b[39m\u001b[1m\u001b[2m 87.65 kB\u001b[22m\u001b[1m\u001b[22m\u001b[2m │ gzip: 29.95 kB\u001b[22m\n\u001b[2mdist/\u001b[22m\u001b[36massets/index-D1DGLj7q.js                   \u001b[39m\u001b[1m\u001b[2m 91.22 kB\u001b[22m\u001b[1m\u001b[22m\u001b[2m │ gzip: 25.31 kB\u001b[22m\n\u001b[2mdist/\u001b[22m\u001b[36massets/vue-vendor-Bpk2tobt.js              \u001b[39m\u001b[1m\u001b[2m109.68 kB\u001b[22m\u001b[1m\u001b[22m\u001b[2m │ gzip: 42.86 kB\u001b[22m\n\u001b[32m✓ built in 13.11s\u001b[39m\n"
    }
  ]
}