{
  "generatedAt": "2026-04-16T06:29:33.570Z",
  "baseUrl": "https://cloud1-9gywyqe49638e46f.service.tcloudbase.com/admin/api",
  "ok": true,
  "results": [
    {
      "name": "products",
      "ok": true,
      "status": 200,
      "count": 11,
      "issues": []
    },
    {
      "name": "orders",
      "ok": true,
      "status": 200,
      "count": 20,
      "issues": []
    },
    {
      "name": "users",
      "ok": true,
      "status": 200,
      "count": 20,
      "issues": []
    },
    {
      "name": "refunds",
      "ok": true,
      "status": 200,
      "count": 20,
      "issues": []
    },
    {
      "name": "withdrawals",
      "ok": true,
      "status": 200,
      "count": 5,
      "issues": []
    },
    {
      "name": "commissions",
      "ok": true,
      "status": 200,
      "count": 5,
      "issues": []
    },
    {
      "name": "group-buys",
      "ok": true,
      "status": 200,
      "count": 2,
      "issues": []
    },
    {
      "name": "lottery-prizes",
      "ok": true,
      "status": 200,
      "count": 13,
      "issues": []
    },
    {
      "name": "pickup-stations",
      "ok": true,
      "status": 200,
      "count": 3,
      "issues": []
    },
    {
      "name": "activity-links",
      "ok": true,
      "status": 200,
      "issues": []
    }
  ]
}